{
	"name": "the garden",
	"radius": 2000,
	"baseColor": "#1144ff",
	"perimeterColor": "#a0522d",
	"gardenDay": 2414,
	"currentCenter": {
	  "x": 0,
	  "y": 0
	},
	"data": {
	  "models": [
		{
		  "name": "Dandelion-36",
		  "evolution": {
			"maxAge": 120,
			"seedsDay": 33,
			"seeds": {
			  "min": 5,
			  "max": 9
			},
			"seedCountDown": -5,
			"seedSuccesRate": 0.7,
			"seedDistance": {
			  "min": 150,
			  "max": 370
			}
		  },
		  "leaves": {
			"shape": "lines",
			"number": 36,
			"leafModel": {
			  "size": {
				"min": 9,
				"max": 36,
				"growthPerDay": 2
			  },
			  "angles": [
				0,
				0.1745,
				0.349,
				0.5235,
				0.698,
				0.8725,
				1.047,
				1.2215,
				1.396,
				1.5705,
				1.745,
				1.9195,
				2.094,
				2.2685,
				2.443,
				2.6175,
				2.792,
				2.9665,
				3.141,
				3.3155,
				3.49,
				3.6645,
				3.839,
				4.0135,
				4.188,
				4.3625,
				4.537,
				4.7115,
				4.886,
				5.0605,
				5.235,
				5.4095,
				5.584,
				5.7585,
				5.933,
				6.1075
			  ],
			  "color": "#d233d2"
			}
		  }
		},
		{
		  "name": "Dandelion-36b",
		  "evolution": {
			"maxAge": 120,
			"seedsDay": 33,
			"seeds": {
			  "min": 5,
			  "max": 9
			},
			"seedCountDown": -5,
			"seedSuccesRate": 0.7,
			"seedDistance": {
			  "min": 150,
			  "max": 370
			}
		  },
		  "leaves": {
			"shape": "lines",
			"number": 36,
			"leafModel": {
			  "size": {
				"min": 10,
				"max": 39,
				"growthPerDay": 2
			  },
			  "angles": [
				0,
				0.1745,
				0.349,
				0.5235,
				0.698,
				0.8725,
				1.047,
				1.2215,
				1.396,
				1.5705,
				1.745,
				1.9195,
				2.094,
				2.2685,
				2.443,
				2.6175,
				2.792,
				2.9665,
				3.141,
				3.3155,
				3.49,
				3.6645,
				3.839,
				4.0135,
				4.188,
				4.3625,
				4.537,
				4.7115,
				4.886,
				5.0605,
				5.235,
				5.4095,
				5.584,
				5.7585,
				5.933,
				6.1075
			  ],
			  "color": "#660066"
			}
		  }
		},
		{
		  "name": "Spirula-10",
		  "evolution": {
			"maxAge": 150,
			"seedsDay": 22,
			"seeds": {
			  "min": 5,
			  "max": 12
			},
			"seedCountDown": -4,
			"seedSuccesRate": 0.7,
			"seedDistance": {
			  "min": 250,
			  "max": 520
			}
		  },
		  "leaves": {
			"shape": "double-curve",
			"number": 10,
			"leafModel": {
			  "size": {
				"min": 15,
				"max": 121,
				"growthPerDay": 5
			  },
			  "angles": [
				0,
				0.6,
				1.2,
				1.8,
				2.5,
				3.1,
				3.7,
				4.3,
				5,
				5.6
			  ],
			  "color": "#bbccff",
			  "matrix": [
				{
				  "x": 0,
				  "y": -0.353125
				},
				{
				  "x": -0.24375,
				  "y": -0.278125
				},
				{
				  "x": -0.0234375,
				  "y": -0.0078125
				},
				{
				  "x": 0,
				  "y": -0.353125
				},
				{
				  "x": 0,
				  "y": -0.353125
				},
				{
				  "x": 0.23125,
				  "y": -0.3109375
				},
				{
				  "x": 0.046875,
				  "y": -0.028125
				},
				{
				  "x": 0,
				  "y": -0.353125
				}
			  ]
			}
		  }
		},
		{
		  "name": "Clover-4",
		  "protectRadius": {
			"min": 20,
			"max": 140,
			"growthPerDay": 2,
			"color": "#1100aa",
			"radius": null
		  },
		  "evolution": {
			"maxAge": 99,
			"seedsDay": 33,
			"seeds": {
			  "min": 6,
			  "max": 13
			},
			"seedCountDown": -6,
			"seedSuccesRate": 0.68,
			"seedDistance": {
			  "min": 250,
			  "max": 320
			}
		  },
		  "leaves": {
			"shape": "double-bezier",
			"number": 4,
			"leafModel": {
			  "size": {
				"min": 10,
				"max": 80,
				"growthPerDay": 2
			  },
			  "angles": [
				1.21,
				2.8,
				4.5,
				6.1
			  ],
			  "color": "#00aa00",
			  "matrix": [
				{
				  "x": -0.3,
				  "y": 0.4
				},
				{
				  "x": 0,
				  "y": 0.6
				},
				{
				  "x": 0,
				  "y": 0
				},
				{
				  "x": -0.35,
				  "y": 0.4
				},
				{
				  "x": 0.3,
				  "y": 0.4
				},
				{
				  "x": 0,
				  "y": 0.6
				},
				{
				  "x": 0,
				  "y": 0
				},
				{
				  "x": 0.35,
				  "y": 0.4
				}
			  ]
			}
		  }
		},
		{
		  "name": "Clover-3",
		  "evolution": {
			"maxAge": 99,
			"seedsDay": 35,
			"seeds": {
			  "min": 4,
			  "max": 7
			},
			"seedCountDown": -6,
			"seedSuccesRate": 0.75,
			"seedDistance": {
			  "min": 170,
			  "max": 340
			}
		  },
		  "leaves": {
			"shape": "double-bezier",
			"number": 3,
			"leafModel": {
			  "size": {
				"min": 12,
				"max": 120,
				"growthPerDay": 3
			  },
			  "angles": [
				2.01,
				4,
				6.1
			  ],
			  "color": "#00aa00",
			  "matrix": [
				{
				  "x": -0.3,
				  "y": 0.4
				},
				{
				  "x": 0,
				  "y": 0.6
				},
				{
				  "x": 0,
				  "y": 0
				},
				{
				  "x": -0.35,
				  "y": 0.4
				},
				{
				  "x": 0.3,
				  "y": 0.4
				},
				{
				  "x": 0,
				  "y": 0.6
				},
				{
				  "x": 0,
				  "y": 0
				},
				{
				  "x": 0.35,
				  "y": 0.4
				}
			  ]
			}
		  }
		},
		{
		  "name": "Lilium-7",
		  "evolution": {
			"maxAge": 170,
			"seedsDay": 42,
			"seeds": {
			  "min": 3,
			  "max": 6
			},
			"seedCountDown": -7,
			"seedSuccesRate": 0.7,
			"seedDistance": {
			  "min": 75,
			  "max": 370
			}
		  },
		  "leaves": {
			"shape": "double-curve",
			"number": 7,
			"leafModel": {
			  "size": {
				"min": 30,
				"max": 120,
				"growthPerDay": 9
			  },
			  "angles": [
				0.1,
				0.9,
				1.7,
				2.67,
				3.55,
				4.28,
				5.15
			  ],
			  "color": "#4DBDF2",
			  "matrix": [
				{
				  "x": 0.49642857142857144,
				  "y": -0.8749999999999999
				},
				{
				  "x": 0,
				  "y": 0
				},
				{
				  "x": 0,
				  "y": 0.6142857142857144
				},
				{
				  "x": 0.9857142857142855,
				  "y": 0.37142857142857133
				},
				{
				  "x": 0.49642857142857144,
				  "y": -0.8749999999999999
				},
				{
				  "x": 0,
				  "y": 0
				},
				{
				  "x": 0,
				  "y": 0.6071428571428572
				},
				{
				  "x": -0.9321428571428572,
				  "y": 0.4035714285714285
				}
			  ]
			}
		  }
		},
		{
		  "name": "Tiny-6",
		  "evolution": {
			"maxAge": 35,
			"seedsDay": 27,
			"seeds": {
			  "min": 3,
			  "max": 6
			},
			"seedCountDown": -3,
			"seedSuccesRate": 0.4,
			"seedDistance": {
			  "min": 120,
			  "max": 450
			}
		  },
		  "leaves": {
			"shape": "double-curve",
			"number": 6,
			"leafModel": {
			  "size": {
				"min": 15,
				"max": 40,
				"growthPerDay": 1
			  },
			  "angles": [
				0.5,
				1.7,
				2.67,
				3.55,
				4.28,
				5.15
			  ],
			  "color": "#d233d2",
			  "matrix": [
				{
				  "x": 0.49642857142857144,
				  "y": -0.8749999999999999
				},
				{
				  "x": 0,
				  "y": 0
				},
				{
				  "x": 0,
				  "y": 0.6142857142857144
				},
				{
				  "x": 0.9857142857142855,
				  "y": 0.37142857142857133
				},
				{
				  "x": 0.49642857142857144,
				  "y": -0.8749999999999999
				},
				{
				  "x": 0,
				  "y": 0
				},
				{
				  "x": 0,
				  "y": 0.6071428571428572
				},
				{
				  "x": -0.9321428571428572,
				  "y": 0.4035714285714285
				}
			  ]
			}
		  }
		},
		{
		  "name": "Tiny-7",
		  "evolution": {
			"maxAge": 85,
			"seedsDay": 41,
			"seeds": {
			  "min": 2,
			  "max": 5
			},
			"seedCountDown": -5,
			"seedSuccesRate": 0.4,
			"seedDistance": {
			  "min": 160,
			  "max": 415
			}
		  },
		  "leaves": {
			"shape": "double-curve",
			"number": 7,
			"leafModel": {
			  "size": {
				"min": 20,
				"max": 50,
				"growthPerDay": 1
			  },
			  "angles": [
				0.6,
				1.6,
				2.47,
				3.55,
				4.28,
				5.15,
				6
			  ],
			  "color": "#d233d2",
			  "matrix": [
				{
				  "x": 0.49642857142857144,
				  "y": -0.8749999999999999
				},
				{
				  "x": 0,
				  "y": 0
				},
				{
				  "x": 0,
				  "y": 0.6142857142857144
				},
				{
				  "x": 0.9857142857142855,
				  "y": 0.37142857142857133
				},
				{
				  "x": 0.49642857142857144,
				  "y": -0.8749999999999999
				},
				{
				  "x": 0,
				  "y": 0
				},
				{
				  "x": 0,
				  "y": 0.6071428571428572
				},
				{
				  "x": -0.9321428571428572,
				  "y": 0.4035714285714285
				}
			  ]
			}
		  }
		},
		{
		  "name": "Xelium-8",
		  "evolution": {
			"maxAge": 120,
			"seedsDay": 37,
			"seeds": {
			  "min": 6,
			  "max": 9
			},
			"seedCountDown": -7,
			"seedSuccesRate": 0.7,
			"seedDistance": {
			  "min": 165,
			  "max": 345
			}
		  },
		  "leaves": {
			"shape": "double-curve",
			"number": 8,
			"leafModel": {
			  "size": {
				"min": 20,
				"max": 100,
				"growthPerDay": 11
			  },
			  "angles": [
				0.4,
				1.9,
				2.67,
				3.45,
				4.28,
				5.15,
				6,
				7.3
			  ],
			  "color": "#d26633",
			  "matrix": [
				{
				  "x": 0.49642857142857144,
				  "y": -0.8749999999999999
				},
				{
				  "x": 0,
				  "y": 0
				},
				{
				  "x": 0,
				  "y": 0.6142857142857144
				},
				{
				  "x": 0.9857142857142855,
				  "y": 0.37142857142857133
				},
				{
				  "x": 0.49642857142857144,
				  "y": -0.8749999999999999
				},
				{
				  "x": 0,
				  "y": 0
				},
				{
				  "x": 0,
				  "y": 0.6071428571428572
				},
				{
				  "x": -0.9321428571428572,
				  "y": 0.4035714285714285
				}
			  ]
			}
		  }
		},
		{
		  "name": "Pelium-6",
		  "evolution": {
			"maxAge": 110,
			"seedsDay": 43,
			"seeds": {
			  "min": 6,
			  "max": 9
			},
			"seedCountDown": -7,
			"seedSuccesRate": 0.7,
			"seedDistance": {
			  "min": 139,
			  "max": 289
			}
		  },
		  "leaves": {
			"shape": "double-curve",
			"number": 6,
			"leafModel": {
			  "size": {
				"min": 20,
				"max": 100,
				"growthPerDay": 7
			  },
			  "angles": [
				0.5,
				1.7,
				2.67,
				3.55,
				4.28,
				5.15
			  ],
			  "color": "#F24DBD",
			  "matrix": [
				{
				  "x": 0.49642857142857144,
				  "y": -0.8749999999999999
				},
				{
				  "x": 0,
				  "y": 0
				},
				{
				  "x": 0,
				  "y": 0.6142857142857144
				},
				{
				  "x": 0.9857142857142855,
				  "y": 0.37142857142857133
				},
				{
				  "x": 0.49642857142857144,
				  "y": -0.8749999999999999
				},
				{
				  "x": 0,
				  "y": 0
				},
				{
				  "x": 0,
				  "y": 0.6071428571428572
				},
				{
				  "x": -0.9321428571428572,
				  "y": 0.4035714285714285
				}
			  ]
			}
		  }
		}
	  ],
	  "floor": {
		"shapes": [
		  {
			"name": "sea",
			"distance": 0,
			"angleToOrigine": 0,
			"innerRotation": 0,
			"color": "#009966",
			"shape": "polygon",
			"colliderMode": "water",
			"size": [
			  2200
			],
			"opacity": 1,
			"matrix": [
			  {
				"x": -0.805,
				"y": -0.725
			  },
			  {
				"x": -0.785,
				"y": -0.69
			  },
			  {
				"x": -0.795,
				"y": -0.635
			  },
			  {
				"x": -0.83,
				"y": -0.595
			  },
			  {
				"x": -0.87,
				"y": -0.54
			  },
			  {
				"x": -0.885,
				"y": -0.46
			  },
			  {
				"x": -0.885,
				"y": -0.405
			  },
			  {
				"x": -0.845,
				"y": -0.36
			  },
			  {
				"x": -0.81,
				"y": -0.305
			  },
			  {
				"x": -0.8,
				"y": -0.265
			  },
			  {
				"x": -0.81,
				"y": -0.22
			  },
			  {
				"x": -0.84,
				"y": -0.12
			  },
			  {
				"x": -0.87,
				"y": -0.09
			  },
			  {
				"x": -0.9,
				"y": -0.06
			  },
			  {
				"x": -0.92,
				"y": -0.015
			  },
			  {
				"x": -0.9,
				"y": 0.02
			  },
			  {
				"x": -0.87,
				"y": 0.05
			  },
			  {
				"x": -0.81,
				"y": 0.055
			  },
			  {
				"x": -0.785,
				"y": 0.07
			  },
			  {
				"x": -0.78,
				"y": 0.09
			  },
			  {
				"x": -0.785,
				"y": 0.125
			  },
			  {
				"x": -0.805,
				"y": 0.155
			  },
			  {
				"x": -0.825,
				"y": 0.185
			  },
			  {
				"x": -0.83,
				"y": 0.2
			  },
			  {
				"x": -0.82,
				"y": 0.295
			  },
			  {
				"x": -0.855,
				"y": 0.315
			  },
			  {
				"x": -0.9,
				"y": 0.36
			  },
			  {
				"x": -0.9,
				"y": 0.4
			  },
			  {
				"x": -0.875,
				"y": 0.465
			  },
			  {
				"x": -0.83,
				"y": 0.525
			  },
			  {
				"x": -0.81,
				"y": 0.56
			  },
			  {
				"x": -0.8,
				"y": 0.6
			  },
			  {
				"x": -0.835,
				"y": 0.645
			  },
			  {
				"x": -0.855,
				"y": 0.66
			  },
			  {
				"x": -0.9,
				"y": 0.665
			  },
			  {
				"x": -0.92,
				"y": 0.695
			  },
			  {
				"x": -0.945,
				"y": 0.745
			  },
			  {
				"x": -0.915,
				"y": 0.77
			  },
			  {
				"x": -0.865,
				"y": 0.805
			  },
			  {
				"x": -0.85,
				"y": 0.875
			  },
			  {
				"x": -0.875,
				"y": 0.92
			  },
			  {
				"x": -0.835,
				"y": 0.935
			  },
			  {
				"x": -0.765,
				"y": 0.95
			  },
			  {
				"x": -0.69,
				"y": 0.95
			  },
			  {
				"x": -0.64,
				"y": 0.925
			  },
			  {
				"x": -0.63,
				"y": 0.865
			  },
			  {
				"x": -0.595,
				"y": 0.835
			  },
			  {
				"x": -0.53,
				"y": 0.81
			  },
			  {
				"x": -0.495,
				"y": 0.85
			  },
			  {
				"x": -0.42,
				"y": 0.91
			  },
			  {
				"x": -0.375,
				"y": 0.925
			  },
			  {
				"x": -0.285,
				"y": 0.915
			  },
			  {
				"x": -0.175,
				"y": 0.88
			  },
			  {
				"x": -0.115,
				"y": 0.905
			  },
			  {
				"x": -0.055,
				"y": 0.93
			  },
			  {
				"x": 0.075,
				"y": 0.915
			  },
			  {
				"x": 0.185,
				"y": 0.905
			  },
			  {
				"x": 0.275,
				"y": 0.86
			  },
			  {
				"x": 0.325,
				"y": 0.9
			  },
			  {
				"x": 0.43,
				"y": 0.94
			  },
			  {
				"x": 0.55,
				"y": 0.945
			  },
			  {
				"x": 0.615,
				"y": 0.91
			  },
			  {
				"x": 0.755,
				"y": 0.865
			  },
			  {
				"x": 0.795,
				"y": 0.77
			  },
			  {
				"x": 0.825,
				"y": 0.69
			  },
			  {
				"x": 0.865,
				"y": 0.575
			  },
			  {
				"x": 0.83,
				"y": 0.46
			  },
			  {
				"x": 0.75,
				"y": 0.42
			  },
			  {
				"x": 0.705,
				"y": 0.315
			  },
			  {
				"x": 0.78,
				"y": 0.275
			  },
			  {
				"x": 0.84,
				"y": 0.275
			  },
			  {
				"x": 0.89,
				"y": 0.215
			  },
			  {
				"x": 0.905,
				"y": 0.05
			  },
			  {
				"x": 0.87,
				"y": -0.02
			  },
			  {
				"x": 0.785,
				"y": -0.13
			  },
			  {
				"x": 0.82,
				"y": -0.25
			  },
			  {
				"x": 0.87,
				"y": -0.36
			  },
			  {
				"x": 0.945,
				"y": -0.505
			  },
			  {
				"x": 0.86,
				"y": -0.645
			  },
			  {
				"x": 0.785,
				"y": -0.675
			  },
			  {
				"x": 0.695,
				"y": -0.72
			  },
			  {
				"x": 0.605,
				"y": -0.755
			  },
			  {
				"x": 0.54,
				"y": -0.81
			  },
			  {
				"x": 0.52,
				"y": -0.88
			  },
			  {
				"x": 0.525,
				"y": -0.93
			  },
			  {
				"x": 0.46,
				"y": -0.93
			  },
			  {
				"x": 0.405,
				"y": -0.925
			  },
			  {
				"x": 0.325,
				"y": -0.885
			  },
			  {
				"x": 0.235,
				"y": -0.885
			  },
			  {
				"x": 0.185,
				"y": -0.945
			  },
			  {
				"x": 0.15,
				"y": -0.94
			  },
			  {
				"x": 0.12,
				"y": -0.91
			  },
			  {
				"x": 0.1,
				"y": -0.82
			  },
			  {
				"x": 0.125,
				"y": -0.74
			  },
			  {
				"x": 0.11,
				"y": -0.685
			  },
			  {
				"x": 0.015,
				"y": -0.685
			  },
			  {
				"x": -0.075,
				"y": -0.715
			  },
			  {
				"x": -0.14,
				"y": -0.785
			  },
			  {
				"x": -0.16,
				"y": -0.86
			  },
			  {
				"x": -0.19,
				"y": -0.885
			  },
			  {
				"x": -0.305,
				"y": -0.855
			  },
			  {
				"x": -0.43,
				"y": -0.85
			  },
			  {
				"x": -0.5,
				"y": -0.89
			  },
			  {
				"x": -0.565,
				"y": -0.89
			  },
			  {
				"x": -0.625,
				"y": -0.87
			  },
			  {
				"x": -0.68,
				"y": -0.845
			  },
			  {
				"x": -0.74,
				"y": -0.795
			  },
			  {
				"x": -0.75,
				"y": -0.765
			  },
			  {
				"x": -0.805,
				"y": -0.725
			  }
			],
			"position": {
			  "x": 0,
			  "y": 0
			}
		  },
		  {
			"distance": 0,
			"angleToOrigine": 0,
			"color": "#ffffff",
			"repeat": 3,
			"shape": "circle",
			"way": "up",
			"size": [
			  250
			],
			"opacity": 0.1,
			"position": {
			  "x": 0,
			  "y": 0
			}
		  },
		  {
			"distance": 300,
			"angleToOrigine": 0.7,
			"color": "#ffffff",
			"repeat": 3,
			"shape": "circle",
			"way": "up",
			"size": [
			  300
			],
			"opacity": 0.1,
			"position": {
			  "x": 229,
			  "y": -194
			}
		  },
		  {
			"distance": 1000,
			"name": "western garden",
			"specific": "auto-garden",
			"angleToOrigine": 2.7,
			"color": "#009966",
			"repeat": 3,
			"shape": "circle",
			"way": "up",
			"size": [
			  200
			],
			"opacity": 0.1,
			"position": {
			  "x": -905,
			  "y": -428
			}
		  },
		  {
			"name": "south-lake",
			"distance": 1000,
			"angleToOrigine": 4.5,
			"innerRotation": 0.6,
			"color": "#1144ff",
			"shape": "polygon",
			"colliderMode": "water",
			"size": [
			  480
			],
			"opacity": 1,
			"matrix": [
			  {
				"x": -0.465,
				"y": -0.585
			  },
			  {
				"x": -0.55,
				"y": -0.495
			  },
			  {
				"x": -0.61,
				"y": -0.44
			  },
			  {
				"x": -0.66,
				"y": -0.315
			  },
			  {
				"x": -0.75,
				"y": -0.24
			  },
			  {
				"x": -0.785,
				"y": -0.205
			  },
			  {
				"x": -0.785,
				"y": -0.135
			  },
			  {
				"x": -0.8,
				"y": -0.1
			  },
			  {
				"x": -0.785,
				"y": 0.02
			  },
			  {
				"x": -0.73,
				"y": 0.09
			  },
			  {
				"x": -0.68,
				"y": 0.13
			  },
			  {
				"x": -0.595,
				"y": 0.185
			  },
			  {
				"x": -0.505,
				"y": 0.215
			  },
			  {
				"x": -0.415,
				"y": 0.275
			  },
			  {
				"x": -0.4,
				"y": 0.355
			  },
			  {
				"x": -0.36,
				"y": 0.45
			  },
			  {
				"x": -0.325,
				"y": 0.52
			  },
			  {
				"x": -0.24,
				"y": 0.565
			  },
			  {
				"x": -0.145,
				"y": 0.615
			  },
			  {
				"x": -0.045,
				"y": 0.62
			  },
			  {
				"x": 0.12,
				"y": 0.615
			  },
			  {
				"x": 0.255,
				"y": 0.595
			  },
			  {
				"x": 0.345,
				"y": 0.645
			  },
			  {
				"x": 0.43,
				"y": 0.62
			  },
			  {
				"x": 0.5,
				"y": 0.57
			  },
			  {
				"x": 0.565,
				"y": 0.465
			  },
			  {
				"x": 0.595,
				"y": 0.36
			  },
			  {
				"x": 0.62,
				"y": 0.21
			  },
			  {
				"x": 0.665,
				"y": 0.11
			  },
			  {
				"x": 0.805,
				"y": -0.035
			  },
			  {
				"x": 0.785,
				"y": -0.14
			  },
			  {
				"x": 0.69,
				"y": -0.285
			  },
			  {
				"x": 0.555,
				"y": -0.475
			  },
			  {
				"x": 0.325,
				"y": -0.57
			  },
			  {
				"x": 0.175,
				"y": -0.555
			  },
			  {
				"x": -0.055,
				"y": -0.565
			  },
			  {
				"x": -0.145,
				"y": -0.59
			  },
			  {
				"x": -0.255,
				"y": -0.635
			  },
			  {
				"x": -0.37,
				"y": -0.64
			  },
			  {
				"x": -0.465,
				"y": -0.585
			  }
			],
			"position": {
			  "x": -211,
			  "y": 977
			}
		  },
		  {
			"name": "south-lake-1",
			"distance": 1000,
			"angleToOrigine": 4.5,
			"innerRotation": 0.69,
			"color": "#DFE7FF",
			"shape": "polygon",
			"size": [
			  450
			],
			"opacity": 0.4,
			"matrix": [
			  {
				"x": -0.465,
				"y": -0.585
			  },
			  {
				"x": -0.55,
				"y": -0.495
			  },
			  {
				"x": -0.61,
				"y": -0.44
			  },
			  {
				"x": -0.66,
				"y": -0.315
			  },
			  {
				"x": -0.75,
				"y": -0.24
			  },
			  {
				"x": -0.785,
				"y": -0.205
			  },
			  {
				"x": -0.785,
				"y": -0.135
			  },
			  {
				"x": -0.8,
				"y": -0.1
			  },
			  {
				"x": -0.785,
				"y": 0.02
			  },
			  {
				"x": -0.73,
				"y": 0.09
			  },
			  {
				"x": -0.68,
				"y": 0.13
			  },
			  {
				"x": -0.595,
				"y": 0.185
			  },
			  {
				"x": -0.505,
				"y": 0.215
			  },
			  {
				"x": -0.415,
				"y": 0.275
			  },
			  {
				"x": -0.4,
				"y": 0.355
			  },
			  {
				"x": -0.36,
				"y": 0.45
			  },
			  {
				"x": -0.325,
				"y": 0.52
			  },
			  {
				"x": -0.24,
				"y": 0.565
			  },
			  {
				"x": -0.145,
				"y": 0.615
			  },
			  {
				"x": -0.045,
				"y": 0.62
			  },
			  {
				"x": 0.12,
				"y": 0.615
			  },
			  {
				"x": 0.255,
				"y": 0.595
			  },
			  {
				"x": 0.345,
				"y": 0.645
			  },
			  {
				"x": 0.43,
				"y": 0.62
			  },
			  {
				"x": 0.5,
				"y": 0.57
			  },
			  {
				"x": 0.565,
				"y": 0.465
			  },
			  {
				"x": 0.595,
				"y": 0.36
			  },
			  {
				"x": 0.62,
				"y": 0.21
			  },
			  {
				"x": 0.665,
				"y": 0.11
			  },
			  {
				"x": 0.805,
				"y": -0.035
			  },
			  {
				"x": 0.785,
				"y": -0.14
			  },
			  {
				"x": 0.69,
				"y": -0.285
			  },
			  {
				"x": 0.555,
				"y": -0.475
			  },
			  {
				"x": 0.325,
				"y": -0.57
			  },
			  {
				"x": 0.175,
				"y": -0.555
			  },
			  {
				"x": -0.055,
				"y": -0.565
			  },
			  {
				"x": -0.145,
				"y": -0.59
			  },
			  {
				"x": -0.255,
				"y": -0.635
			  },
			  {
				"x": -0.37,
				"y": -0.64
			  },
			  {
				"x": -0.465,
				"y": -0.585
			  }
			],
			"position": {
			  "x": -211,
			  "y": 977
			}
		  },
		  {
			"name": "south-lake-2",
			"distance": 1000,
			"angleToOrigine": 4.5,
			"innerRotation": 0.6,
			"color": "#1144ff",
			"shape": "polygon",
			"size": [
			  370
			],
			"opacity": 1,
			"matrix": [
			  {
				"x": -0.465,
				"y": -0.585
			  },
			  {
				"x": -0.55,
				"y": -0.495
			  },
			  {
				"x": -0.61,
				"y": -0.44
			  },
			  {
				"x": -0.66,
				"y": -0.315
			  },
			  {
				"x": -0.75,
				"y": -0.24
			  },
			  {
				"x": -0.785,
				"y": -0.205
			  },
			  {
				"x": -0.785,
				"y": -0.135
			  },
			  {
				"x": -0.8,
				"y": -0.1
			  },
			  {
				"x": -0.785,
				"y": 0.02
			  },
			  {
				"x": -0.73,
				"y": 0.09
			  },
			  {
				"x": -0.68,
				"y": 0.13
			  },
			  {
				"x": -0.595,
				"y": 0.185
			  },
			  {
				"x": -0.505,
				"y": 0.215
			  },
			  {
				"x": -0.415,
				"y": 0.275
			  },
			  {
				"x": -0.4,
				"y": 0.355
			  },
			  {
				"x": -0.36,
				"y": 0.45
			  },
			  {
				"x": -0.325,
				"y": 0.52
			  },
			  {
				"x": -0.24,
				"y": 0.565
			  },
			  {
				"x": -0.145,
				"y": 0.615
			  },
			  {
				"x": -0.045,
				"y": 0.62
			  },
			  {
				"x": 0.12,
				"y": 0.615
			  },
			  {
				"x": 0.255,
				"y": 0.595
			  },
			  {
				"x": 0.345,
				"y": 0.645
			  },
			  {
				"x": 0.43,
				"y": 0.62
			  },
			  {
				"x": 0.5,
				"y": 0.57
			  },
			  {
				"x": 0.565,
				"y": 0.465
			  },
			  {
				"x": 0.595,
				"y": 0.36
			  },
			  {
				"x": 0.62,
				"y": 0.21
			  },
			  {
				"x": 0.665,
				"y": 0.11
			  },
			  {
				"x": 0.805,
				"y": -0.035
			  },
			  {
				"x": 0.785,
				"y": -0.14
			  },
			  {
				"x": 0.69,
				"y": -0.285
			  },
			  {
				"x": 0.555,
				"y": -0.475
			  },
			  {
				"x": 0.325,
				"y": -0.57
			  },
			  {
				"x": 0.175,
				"y": -0.555
			  },
			  {
				"x": -0.055,
				"y": -0.565
			  },
			  {
				"x": -0.145,
				"y": -0.59
			  },
			  {
				"x": -0.255,
				"y": -0.635
			  },
			  {
				"x": -0.37,
				"y": -0.64
			  },
			  {
				"x": -0.465,
				"y": -0.585
			  }
			],
			"position": {
			  "x": -211,
			  "y": 977
			}
		  }
		]
	  },
	  "plants": [
		{
		  "birth": 2265,
		  "distance": 677,
		  "angleToOrigine": -0.8898906346341304,
		  "position": {
			"x": 426,
			"y": 526
		  },
		  "color": "#B24DBD",
		  "shape": "circle",
		  "size": {
			"min": 6,
			"max": 13,
			"growthPerDay": 1
		  },
		  "name": "spirula-2262*2",
		  "innerRotation": 2.476021912723352,
		  "model": "Spirula-10",
		  "stage": 3
		},
		{
		  "birth": 2265,
		  "distance": 579,
		  "angleToOrigine": 0.2480320887518882,
		  "position": {
			"x": 561,
			"y": -143
		  },
		  "color": "#B24DBD",
		  "shape": "circle",
		  "size": {
			"min": 6,
			"max": 13,
			"growthPerDay": 1
		  },
		  "name": "spirula-2262*8",
		  "innerRotation": 5.901859863386925,
		  "model": "Spirula-10",
		  "stage": 2
		},
		{
		  "birth": 2265,
		  "distance": 1183,
		  "angleToOrigine": 0.22946266700617252,
		  "position": {
			"x": 1151,
			"y": -270
		  },
		  "color": "#B24DBD",
		  "shape": "circle",
		  "size": {
			"min": 6,
			"max": 13,
			"growthPerDay": 1
		  },
		  "name": "spirula-2262*10",
		  "innerRotation": 4.7589798781376365,
		  "model": "Spirula-10",
		  "stage": 2
		},
		{
		  "birth": 2265,
		  "distance": 448,
		  "angleToOrigine": -0.6216977108935839,
		  "position": {
			"x": 364,
			"y": 260
		  },
		  "color": "#B24DBD",
		  "shape": "circle",
		  "size": {
			"min": 6,
			"max": 13,
			"growthPerDay": 1
		  },
		  "name": "spirula-2262*11",
		  "innerRotation": 1.3069887143394732,
		  "model": "Spirula-10",
		  "stage": 2
		},
		{
		  "birth": 2266,
		  "distance": 1317,
		  "angleToOrigine": 0.3865702498655674,
		  "position": {
			"x": 1219,
			"y": -497
		  },
		  "color": "#B24DBD",
		  "shape": "circle",
		  "size": {
			"min": 6,
			"max": 13,
			"growthPerDay": 1
		  },
		  "name": "spirula-2263*5",
		  "innerRotation": 1.9130142159942918,
		  "model": "Spirula-10",
		  "stage": 1
		},
		{
		  "birth": 2266,
		  "distance": 1649,
		  "angleToOrigine": 0.2523235686648382,
		  "position": {
			"x": 1596,
			"y": -412
		  },
		  "color": "#B24DBD",
		  "shape": "circle",
		  "size": {
			"min": 6,
			"max": 13,
			"growthPerDay": 1
		  },
		  "name": "spirula-2263*8",
		  "innerRotation": 0.6755893185978051,
		  "model": "Spirula-10",
		  "stage": 1
		},
		{
		  "birth": 2266,
		  "distance": 922,
		  "angleToOrigine": 1.5159315350258185,
		  "position": {
			"x": 50,
			"y": -921
		  },
		  "color": "#B24DBD",
		  "shape": "circle",
		  "size": {
			"min": 6,
			"max": 13,
			"growthPerDay": 1
		  },
		  "name": "spirula-2263*2",
		  "innerRotation": 6.001375794405657,
		  "model": "Spirula-10",
		  "stage": 1
		},
		{
		  "birth": 2266,
		  "distance": 1570,
		  "angleToOrigine": -0.7294057961910357,
		  "position": {
			"x": 1170,
			"y": 1046
		  },
		  "color": "#B24DBD",
		  "shape": "circle",
		  "size": {
			"min": 6,
			"max": 13,
			"growthPerDay": 1
		  },
		  "name": "spirula-2263*5",
		  "innerRotation": 2.932025980298331,
		  "model": "Spirula-10",
		  "stage": 1
		},
		{
		  "birth": 2266,
		  "distance": 1667,
		  "angleToOrigine": -0.783598525268293,
		  "position": {
			"x": 1180,
			"y": 1176
		  },
		  "color": "#B24DBD",
		  "shape": "circle",
		  "size": {
			"min": 6,
			"max": 13,
			"growthPerDay": 1
		  },
		  "name": "spirula-2263*7",
		  "innerRotation": 6.157121944781193,
		  "model": "Spirula-10",
		  "stage": 1
		},
		{
		  "birth": 2266,
		  "distance": 1232,
		  "angleToOrigine": -1.4563662879382613,
		  "position": {
			"x": 140,
			"y": 1223
		  },
		  "color": "#B24DBD",
		  "shape": "circle",
		  "size": {
			"min": 6,
			"max": 13,
			"growthPerDay": 1
		  },
		  "name": "spirula-2263*8",
		  "innerRotation": 2.712016764599122,
		  "model": "Spirula-10",
		  "stage": 1
		},
		{
		  "birth": 2266,
		  "distance": 1009,
		  "angleToOrigine": -0.14555421750120082,
		  "position": {
			"x": 998,
			"y": 146
		  },
		  "color": "#B24DBD",
		  "shape": "circle",
		  "size": {
			"min": 6,
			"max": 13,
			"growthPerDay": 1
		  },
		  "name": "spirula-2263*2",
		  "innerRotation": 3.6936661130515565,
		  "model": "Spirula-10",
		  "stage": 1
		},
		{
		  "birth": 2266,
		  "distance": 775,
		  "angleToOrigine": 0.06739090789953495,
		  "position": {
			"x": 773,
			"y": -53
		  },
		  "color": "#B24DBD",
		  "shape": "circle",
		  "size": {
			"min": 6,
			"max": 13,
			"growthPerDay": 1
		  },
		  "name": "spirula-2263*7",
		  "innerRotation": 5.8884238417022,
		  "model": "Spirula-10",
		  "stage": 1
		},
		{
		  "birth": 2266,
		  "distance": 1198,
		  "angleToOrigine": -1.3776266349898614,
		  "position": {
			"x": 229,
			"y": 1175
		  },
		  "color": "#B24DBD",
		  "shape": "circle",
		  "size": {
			"min": 6,
			"max": 13,
			"growthPerDay": 1
		  },
		  "name": "spirula-2263*5",
		  "innerRotation": 4.925232769632719,
		  "model": "Spirula-10",
		  "stage": 1
		},
		{
		  "birth": 2266,
		  "distance": 1246,
		  "angleToOrigine": -0.7388827839368042,
		  "position": {
			"x": 921,
			"y": 839
		  },
		  "color": "#B24DBD",
		  "shape": "circle",
		  "size": {
			"min": 6,
			"max": 13,
			"growthPerDay": 1
		  },
		  "name": "spirula-2263*6",
		  "innerRotation": 5.047850116036066,
		  "model": "Spirula-10",
		  "stage": 1
		},
		{
		  "birth": 2266,
		  "distance": 1562,
		  "angleToOrigine": -0.8773278178945341,
		  "position": {
			"x": 998,
			"y": 1201
		  },
		  "color": "#B24DBD",
		  "shape": "circle",
		  "size": {
			"min": 6,
			"max": 13,
			"growthPerDay": 1
		  },
		  "name": "spirula-2263*7",
		  "innerRotation": 1.9475768757982808,
		  "model": "Spirula-10",
		  "stage": 1
		},
		{
		  "birth": 2266,
		  "distance": 1398,
		  "angleToOrigine": -0.7410781348748748,
		  "position": {
			"x": 1031,
			"y": 943
		  },
		  "color": "#B24DBD",
		  "shape": "circle",
		  "size": {
			"min": 6,
			"max": 13,
			"growthPerDay": 1
		  },
		  "name": "spirula-2263*10",
		  "innerRotation": 0.5036841064738056,
		  "model": "Spirula-10",
		  "stage": 1
		},
		{
		  "birth": 2266,
		  "distance": 1557,
		  "angleToOrigine": -0.5058265640963275,
		  "position": {
			"x": 1362,
			"y": 754
		  },
		  "color": "#B24DBD",
		  "shape": "circle",
		  "size": {
			"min": 6,
			"max": 13,
			"growthPerDay": 1
		  },
		  "name": "spirula-2263*2",
		  "innerRotation": 2.6948066430619844,
		  "model": "Spirula-10",
		  "stage": 1
		},
		{
		  "birth": 2266,
		  "distance": 1785,
		  "angleToOrigine": -1.2053365098926698,
		  "position": {
			"x": 637,
			"y": 1667
		  },
		  "color": "#B24DBD",
		  "shape": "circle",
		  "size": {
			"min": 6,
			"max": 13,
			"growthPerDay": 1
		  },
		  "name": "spirula-2263*4",
		  "innerRotation": 1.0429633717773976,
		  "model": "Spirula-10",
		  "stage": 1
		},
		{
		  "birth": 2266,
		  "distance": 1600,
		  "angleToOrigine": -1.178768324906149,
		  "position": {
			"x": 611,
			"y": 1478
		  },
		  "color": "#B24DBD",
		  "shape": "circle",
		  "size": {
			"min": 6,
			"max": 13,
			"growthPerDay": 1
		  },
		  "name": "spirula-2263*5",
		  "innerRotation": 2.2936878295446483,
		  "model": "Spirula-10",
		  "stage": 1
		},
		{
		  "birth": 2281,
		  "distance": 1347,
		  "angleToOrigine": 0.054761170195437386,
		  "position": {
			"x": 1344,
			"y": -74
		  },
		  "color": "#B24DBD",
		  "shape": "circle",
		  "size": {
			"min": 6,
			"max": 13,
			"growthPerDay": 1
		  },
		  "name": "spirula-2278*3",
		  "innerRotation": 3.599230327880401,
		  "model": "Spirula-10",
		  "stage": 1
		},
		{
		  "birth": 2281,
		  "distance": 1338,
		  "angleToOrigine": 0.22050878111764308,
		  "position": {
			"x": 1305,
			"y": -293
		  },
		  "color": "#B24DBD",
		  "shape": "circle",
		  "size": {
			"min": 6,
			"max": 13,
			"growthPerDay": 1
		  },
		  "name": "spirula-2278*6",
		  "innerRotation": 1.5632938215909038,
		  "model": "Spirula-10",
		  "stage": 1
		},
		{
		  "birth": 2281,
		  "distance": 1459,
		  "angleToOrigine": 0.04286151059145758,
		  "position": {
			"x": 1457,
			"y": -63
		  },
		  "color": "#B24DBD",
		  "shape": "circle",
		  "size": {
			"min": 6,
			"max": 13,
			"growthPerDay": 1
		  },
		  "name": "spirula-2278*3",
		  "innerRotation": 5.358052493555661,
		  "model": "Spirula-10",
		  "stage": 1
		},
		{
		  "birth": 2281,
		  "distance": 1753,
		  "angleToOrigine": 0.01270873227430529,
		  "position": {
			"x": 1752,
			"y": -23
		  },
		  "color": "#B24DBD",
		  "shape": "circle",
		  "size": {
			"min": 6,
			"max": 13,
			"growthPerDay": 1
		  },
		  "name": "spirula-2278*6",
		  "innerRotation": 2.1880551697840085,
		  "model": "Spirula-10",
		  "stage": 1
		},
		{
		  "birth": 2281,
		  "distance": 1758,
		  "angleToOrigine": -1.5546127687100242,
		  "position": {
			"x": 28,
			"y": 1757
		  },
		  "color": "#B24DBD",
		  "shape": "circle",
		  "size": {
			"min": 6,
			"max": 13,
			"growthPerDay": 1
		  },
		  "name": "spirula-2278*4",
		  "innerRotation": 3.7676121454203404,
		  "model": "Spirula-10",
		  "stage": 1
		},
		{
		  "birth": 2282,
		  "distance": 1357,
		  "angleToOrigine": 0.9568736037150282,
		  "position": {
			"x": 781,
			"y": -1110
		  },
		  "color": "#B24DBD",
		  "shape": "circle",
		  "size": {
			"min": 6,
			"max": 13,
			"growthPerDay": 1
		  },
		  "name": "spirula-2279*3",
		  "innerRotation": 1.0788645824261265,
		  "model": "Spirula-10",
		  "stage": 1
		},
		{
		  "birth": 2282,
		  "distance": 1218,
		  "angleToOrigine": 1.26662208724275,
		  "position": {
			"x": 364,
			"y": -1163
		  },
		  "color": "#B24DBD",
		  "shape": "circle",
		  "size": {
			"min": 6,
			"max": 13,
			"growthPerDay": 1
		  },
		  "name": "spirula-2279*5",
		  "innerRotation": 1.9810660001652667,
		  "model": "Spirula-10",
		  "stage": 1
		},
		{
		  "birth": 2282,
		  "distance": 1601,
		  "angleToOrigine": 1.374121124117634,
		  "position": {
			"x": 312,
			"y": -1571
		  },
		  "color": "#B24DBD",
		  "shape": "circle",
		  "size": {
			"min": 6,
			"max": 13,
			"growthPerDay": 1
		  },
		  "name": "spirula-2279*9",
		  "innerRotation": 5.297657169273097,
		  "model": "Spirula-10",
		  "stage": 1
		},
		{
		  "birth": 2282,
		  "distance": 1246,
		  "angleToOrigine": 1.3081668251926972,
		  "position": {
			"x": 323,
			"y": -1204
		  },
		  "color": "#B24DBD",
		  "shape": "circle",
		  "size": {
			"min": 6,
			"max": 13,
			"growthPerDay": 1
		  },
		  "name": "spirula-2279*2",
		  "innerRotation": 0.4079068099201503,
		  "model": "Spirula-10",
		  "stage": 1
		},
		{
		  "birth": 2282,
		  "distance": 1263,
		  "angleToOrigine": -1.2749855607766047,
		  "position": {
			"x": 368,
			"y": 1208
		  },
		  "color": "#B24DBD",
		  "shape": "circle",
		  "size": {
			"min": 6,
			"max": 13,
			"growthPerDay": 1
		  },
		  "name": "spirula-2279*3",
		  "innerRotation": 0.7121279598145421,
		  "model": "Spirula-10",
		  "stage": 1
		},
		{
		  "birth": 2282,
		  "distance": 1637,
		  "angleToOrigine": 1.2531910790615903,
		  "position": {
			"x": 511,
			"y": -1556
		  },
		  "color": "#B24DBD",
		  "shape": "circle",
		  "size": {
			"min": 6,
			"max": 13,
			"growthPerDay": 1
		  },
		  "name": "spirula-2279*5",
		  "innerRotation": 2.7662195805106498,
		  "model": "Spirula-10",
		  "stage": 1
		},
		{
		  "birth": 2282,
		  "distance": 1742,
		  "angleToOrigine": -1.3543528965345144,
		  "position": {
			"x": 374,
			"y": 1701
		  },
		  "color": "#B24DBD",
		  "shape": "circle",
		  "size": {
			"min": 6,
			"max": 13,
			"growthPerDay": 1
		  },
		  "name": "spirula-2279*7",
		  "innerRotation": 5.123601257874198,
		  "model": "Spirula-10",
		  "stage": 1
		},
		{
		  "birth": 2282,
		  "distance": 200,
		  "angleToOrigine": 1.8688359106871548,
		  "position": {
			"x": -59,
			"y": -192
		  },
		  "color": "#B24DBD",
		  "shape": "circle",
		  "size": {
			"min": 6,
			"max": 13,
			"growthPerDay": 1
		  },
		  "name": "spirula-2279*3",
		  "innerRotation": 1.7797560826250534,
		  "model": "Spirula-10",
		  "stage": 1
		},
		{
		  "birth": 2282,
		  "distance": 514,
		  "angleToOrigine": 1.9716693805283776,
		  "position": {
			"x": -201,
			"y": -474
		  },
		  "color": "#B24DBD",
		  "shape": "circle",
		  "size": {
			"min": 6,
			"max": 13,
			"growthPerDay": 1
		  },
		  "name": "spirula-2279*4",
		  "innerRotation": 4.479897080634183,
		  "model": "Spirula-10",
		  "stage": 1
		},
		{
		  "birth": 2282,
		  "distance": 92,
		  "angleToOrigine": 0.20749622643520266,
		  "position": {
			"x": 90,
			"y": -19
		  },
		  "color": "#B24DBD",
		  "shape": "circle",
		  "size": {
			"min": 6,
			"max": 13,
			"growthPerDay": 1
		  },
		  "name": "spirula-2279*5",
		  "innerRotation": 1.7209213824304082,
		  "model": "Spirula-10",
		  "stage": 1
		},
		{
		  "birth": 2411,
		  "distance": 1425,
		  "angleToOrigine": 0.07613653064366885,
		  "position": {
			"x": 1420,
			"y": -109
		  },
		  "color": "#B24DBD",
		  "shape": "circle",
		  "size": {
			"min": 6,
			"max": 13,
			"growthPerDay": 1
		  },
		  "name": "spirula-2411*4",
		  "innerRotation": 1.702073553402607,
		  "model": "Spirula-10",
		  "stage": 0
		},
		{
		  "birth": 2411,
		  "distance": 1472,
		  "angleToOrigine": 0.07666000941748138,
		  "position": {
			"x": 1467,
			"y": -113
		  },
		  "color": "#B24DBD",
		  "shape": "circle",
		  "size": {
			"min": 6,
			"max": 13,
			"growthPerDay": 1
		  },
		  "name": "spirula-2411*5",
		  "innerRotation": 1.1443176683691383,
		  "model": "Spirula-10",
		  "stage": 0
		},
		{
		  "birth": 2411,
		  "distance": 988,
		  "angleToOrigine": -0.1676424378312157,
		  "position": {
			"x": 974,
			"y": 164
		  },
		  "color": "#B24DBD",
		  "shape": "circle",
		  "size": {
			"min": 6,
			"max": 13,
			"growthPerDay": 1
		  },
		  "name": "spirula-2411*7",
		  "innerRotation": 5.298417732591497,
		  "model": "Spirula-10",
		  "stage": 0
		},
		{
		  "birth": 2411,
		  "distance": 1458,
		  "angleToOrigine": 0.1549725505215701,
		  "position": {
			"x": 1440,
			"y": -226
		  },
		  "color": "#B24DBD",
		  "shape": "circle",
		  "size": {
			"min": 6,
			"max": 13,
			"growthPerDay": 1
		  },
		  "name": "spirula-2411*8",
		  "innerRotation": 0.06815567316364807,
		  "model": "Spirula-10",
		  "stage": 0
		},
		{
		  "birth": 2411,
		  "distance": 1022,
		  "angleToOrigine": -0.23297923907710288,
		  "position": {
			"x": 994,
			"y": 235
		  },
		  "color": "#B24DBD",
		  "shape": "circle",
		  "size": {
			"min": 6,
			"max": 13,
			"growthPerDay": 1
		  },
		  "name": "spirula-2411*10",
		  "innerRotation": 4.316765656840108,
		  "model": "Spirula-10",
		  "stage": 0
		},
		{
		  "birth": 2411,
		  "distance": 1163,
		  "angleToOrigine": -0.21933687408364294,
		  "position": {
			"x": 1135,
			"y": 253
		  },
		  "color": "#B24DBD",
		  "shape": "circle",
		  "size": {
			"min": 6,
			"max": 13,
			"growthPerDay": 1
		  },
		  "name": "spirula-2411*11",
		  "innerRotation": 0.7524523676024013,
		  "model": "Spirula-10",
		  "stage": 0
		},
		{
		  "birth": 2411,
		  "distance": 1542,
		  "angleToOrigine": -0.05036608748436546,
		  "position": {
			"x": 1540,
			"y": 77
		  },
		  "color": "#B24DBD",
		  "shape": "circle",
		  "size": {
			"min": 6,
			"max": 13,
			"growthPerDay": 1
		  },
		  "name": "spirula-2411*12",
		  "innerRotation": 2.951317186513082,
		  "model": "Spirula-10",
		  "stage": 0
		},
		{
		  "birth": 2411,
		  "distance": 1542,
		  "angleToOrigine": -0.10342350554952685,
		  "position": {
			"x": 1533,
			"y": 159
		  },
		  "color": "#B24DBD",
		  "shape": "circle",
		  "size": {
			"min": 6,
			"max": 13,
			"growthPerDay": 1
		  },
		  "name": "spirula-2411*2",
		  "innerRotation": 5.607314523267054,
		  "model": "Spirula-10",
		  "stage": 0
		},
		{
		  "birth": 2411,
		  "distance": 1576,
		  "angleToOrigine": 0.024702386466527483,
		  "position": {
			"x": 1575,
			"y": -39
		  },
		  "color": "#B24DBD",
		  "shape": "circle",
		  "size": {
			"min": 6,
			"max": 13,
			"growthPerDay": 1
		  },
		  "name": "spirula-2411*3",
		  "innerRotation": 2.1832379148168655,
		  "model": "Spirula-10",
		  "stage": 0
		},
		{
		  "birth": 2411,
		  "distance": 1395,
		  "angleToOrigine": -0.0887591503133966,
		  "position": {
			"x": 1389,
			"y": 123
		  },
		  "color": "#B24DBD",
		  "shape": "circle",
		  "size": {
			"min": 6,
			"max": 13,
			"growthPerDay": 1
		  },
		  "name": "spirula-2411*5",
		  "innerRotation": 1.9066072967384717,
		  "model": "Spirula-10",
		  "stage": 0
		},
		{
		  "birth": 2411,
		  "distance": 1638,
		  "angleToOrigine": -0.3651364851939683,
		  "position": {
			"x": 1530,
			"y": 584
		  },
		  "color": "#B24DBD",
		  "shape": "circle",
		  "size": {
			"min": 6,
			"max": 13,
			"growthPerDay": 1
		  },
		  "name": "spirula-2411*10",
		  "innerRotation": 2.507883083982926,
		  "model": "Spirula-10",
		  "stage": 0
		},
		{
		  "birth": 2412,
		  "distance": 1484,
		  "angleToOrigine": -0.1501416063527877,
		  "position": {
			"x": 1467,
			"y": 221
		  },
		  "color": "#B24DBD",
		  "shape": "circle",
		  "size": {
			"min": 6,
			"max": 13,
			"growthPerDay": 1
		  },
		  "name": "spirula-2412*6",
		  "innerRotation": 3.9186849138883577,
		  "model": "Spirula-10",
		  "stage": 0
		},
		{
		  "birth": 2412,
		  "distance": 1593,
		  "angleToOrigine": -0.23982501834392314,
		  "position": {
			"x": 1547,
			"y": 378
		  },
		  "color": "#B24DBD",
		  "shape": "circle",
		  "size": {
			"min": 6,
			"max": 13,
			"growthPerDay": 1
		  },
		  "name": "spirula-2412*12",
		  "innerRotation": 2.284549335128694,
		  "model": "Spirula-10",
		  "stage": 0
		},
		{
		  "birth": 2412,
		  "distance": 1515,
		  "angleToOrigine": -0.24887045122308277,
		  "position": {
			"x": 1468,
			"y": 373
		  },
		  "color": "#B24DBD",
		  "shape": "circle",
		  "size": {
			"min": 6,
			"max": 13,
			"growthPerDay": 1
		  },
		  "name": "spirula-2412*7",
		  "innerRotation": 0.8971244335207078,
		  "model": "Spirula-10",
		  "stage": 0
		},
		{
		  "birth": 2412,
		  "distance": 1749,
		  "angleToOrigine": 1.2233391362688766,
		  "position": {
			"x": 595,
			"y": -1645
		  },
		  "color": "#B24DBD",
		  "shape": "circle",
		  "size": {
			"min": 6,
			"max": 13,
			"growthPerDay": 1
		  },
		  "name": "spirula-2412*2",
		  "innerRotation": 4.0785288102763095,
		  "model": "Spirula-10",
		  "stage": 0
		},
		{
		  "birth": 2412,
		  "distance": 967,
		  "angleToOrigine": 0.852515400556666,
		  "position": {
			"x": 636,
			"y": -729
		  },
		  "color": "#B24DBD",
		  "shape": "circle",
		  "size": {
			"min": 6,
			"max": 13,
			"growthPerDay": 1
		  },
		  "name": "spirula-2412*3",
		  "innerRotation": 5.343125566316627,
		  "model": "Spirula-10",
		  "stage": 0
		},
		{
		  "birth": 2412,
		  "distance": 1388,
		  "angleToOrigine": 1.4191457496280946,
		  "position": {
			"x": 209,
			"y": -1373
		  },
		  "color": "#B24DBD",
		  "shape": "circle",
		  "size": {
			"min": 6,
			"max": 13,
			"growthPerDay": 1
		  },
		  "name": "spirula-2412*5",
		  "innerRotation": 5.620444217843818,
		  "model": "Spirula-10",
		  "stage": 0
		},
		{
		  "birth": 2412,
		  "distance": 819,
		  "angleToOrigine": 1.2868810862201938,
		  "position": {
			"x": 229,
			"y": -787
		  },
		  "color": "#B24DBD",
		  "shape": "circle",
		  "size": {
			"min": 6,
			"max": 13,
			"growthPerDay": 1
		  },
		  "name": "spirula-2412*6",
		  "innerRotation": 1.0805080711894546,
		  "model": "Spirula-10",
		  "stage": 0
		},
		{
		  "birth": 2412,
		  "distance": 1490,
		  "angleToOrigine": -0.5457957925562931,
		  "position": {
			"x": 1273,
			"y": 773
		  },
		  "color": "#B24DBD",
		  "shape": "circle",
		  "size": {
			"min": 6,
			"max": 13,
			"growthPerDay": 1
		  },
		  "name": "spirula-2412*3",
		  "innerRotation": 3.6177526569415153,
		  "model": "Spirula-10",
		  "stage": 0
		},
		{
		  "birth": 2412,
		  "distance": 1234,
		  "angleToOrigine": -0.3756264626963367,
		  "position": {
			"x": 1147,
			"y": 452
		  },
		  "color": "#B24DBD",
		  "shape": "circle",
		  "size": {
			"min": 6,
			"max": 13,
			"growthPerDay": 1
		  },
		  "name": "spirula-2412*5",
		  "innerRotation": 2.5997803381531908,
		  "model": "Spirula-10",
		  "stage": 0
		},
		{
		  "birth": 2412,
		  "distance": 1484,
		  "angleToOrigine": 1.1450547038039232,
		  "position": {
			"x": 612,
			"y": -1352
		  },
		  "color": "#B24DBD",
		  "shape": "circle",
		  "size": {
			"min": 6,
			"max": 13,
			"growthPerDay": 1
		  },
		  "name": "spirula-2412*5",
		  "innerRotation": 3.378181539857767,
		  "model": "Spirula-10",
		  "stage": 0
		},
		{
		  "birth": 2412,
		  "distance": 1356,
		  "angleToOrigine": 1.6773302296372987,
		  "position": {
			"x": -145,
			"y": -1349
		  },
		  "color": "#B24DBD",
		  "shape": "circle",
		  "size": {
			"min": 6,
			"max": 13,
			"growthPerDay": 1
		  },
		  "name": "spirula-2412*6",
		  "innerRotation": 1.5926885309274774,
		  "model": "Spirula-10",
		  "stage": 0
		},
		{
		  "birth": 2412,
		  "distance": 1686,
		  "angleToOrigine": 1.2775693720190924,
		  "position": {
			"x": 487,
			"y": -1615
		  },
		  "color": "#B24DBD",
		  "shape": "circle",
		  "size": {
			"min": 6,
			"max": 13,
			"growthPerDay": 1
		  },
		  "name": "spirula-2412*8",
		  "innerRotation": 4.529965985663223,
		  "model": "Spirula-10",
		  "stage": 0
		},
		{
		  "birth": 2412,
		  "distance": 1630,
		  "angleToOrigine": 0.23066836992370326,
		  "position": {
			"x": 1586,
			"y": -373
		  },
		  "color": "#B24DBD",
		  "shape": "circle",
		  "size": {
			"min": 6,
			"max": 13,
			"growthPerDay": 1
		  },
		  "name": "spirula-2412*2",
		  "innerRotation": 3.645227466490829,
		  "model": "Spirula-10",
		  "stage": 0
		},
		{
		  "birth": 2412,
		  "distance": 1324,
		  "angleToOrigine": 0.010686616064922647,
		  "position": {
			"x": 1323,
			"y": -15
		  },
		  "color": "#B24DBD",
		  "shape": "circle",
		  "size": {
			"min": 6,
			"max": 13,
			"growthPerDay": 1
		  },
		  "name": "spirula-2412*6",
		  "innerRotation": 1.2439333790992888,
		  "model": "Spirula-10",
		  "stage": 0
		},
		{
		  "birth": 2412,
		  "distance": 1797,
		  "angleToOrigine": 0.32152798596052207,
		  "position": {
			"x": 1704,
			"y": -568
		  },
		  "color": "#B24DBD",
		  "shape": "circle",
		  "size": {
			"min": 6,
			"max": 13,
			"growthPerDay": 1
		  },
		  "name": "spirula-2412*4",
		  "innerRotation": 1.415470064376408,
		  "model": "Spirula-10",
		  "stage": 0
		},
		{
		  "birth": 2412,
		  "distance": 1423,
		  "angleToOrigine": 0.262099562637122,
		  "position": {
			"x": 1374,
			"y": -369
		  },
		  "color": "#B24DBD",
		  "shape": "circle",
		  "size": {
			"min": 6,
			"max": 13,
			"growthPerDay": 1
		  },
		  "name": "spirula-2412*7",
		  "innerRotation": 1.8224604241363547,
		  "model": "Spirula-10",
		  "stage": 0
		},
		{
		  "birth": 2412,
		  "distance": 1483,
		  "angleToOrigine": 0.286004198366855,
		  "position": {
			"x": 1422,
			"y": -419
		  },
		  "color": "#B24DBD",
		  "shape": "circle",
		  "size": {
			"min": 6,
			"max": 13,
			"growthPerDay": 1
		  },
		  "name": "spirula-2412*10",
		  "innerRotation": 1.5219156070273545,
		  "model": "Spirula-10",
		  "stage": 0
		},
		{
		  "birth": 2412,
		  "distance": 1491,
		  "angleToOrigine": -1.0950280992520003,
		  "position": {
			"x": 682,
			"y": 1325
		  },
		  "color": "#B24DBD",
		  "shape": "circle",
		  "size": {
			"min": 6,
			"max": 13,
			"growthPerDay": 1
		  },
		  "name": "spirula-2412*2",
		  "innerRotation": 1.0732527509961487,
		  "model": "Spirula-10",
		  "stage": 0
		},
		{
		  "birth": 2412,
		  "distance": 1606,
		  "angleToOrigine": -1.1308655450024974,
		  "position": {
			"x": 683,
			"y": 1453
		  },
		  "color": "#B24DBD",
		  "shape": "circle",
		  "size": {
			"min": 6,
			"max": 13,
			"growthPerDay": 1
		  },
		  "name": "spirula-2412*4",
		  "innerRotation": 5.198557157903764,
		  "model": "Spirula-10",
		  "stage": 0
		},
		{
		  "birth": 2412,
		  "distance": 1156,
		  "angleToOrigine": -1.0793926209450597,
		  "position": {
			"x": 545,
			"y": 1019
		  },
		  "color": "#B24DBD",
		  "shape": "circle",
		  "size": {
			"min": 6,
			"max": 13,
			"growthPerDay": 1
		  },
		  "name": "spirula-2412*8",
		  "innerRotation": 5.887177770057667,
		  "model": "Spirula-10",
		  "stage": 0
		},
		{
		  "birth": 2412,
		  "distance": 727,
		  "angleToOrigine": 1.3040997673754262,
		  "position": {
			"x": 191,
			"y": -702
		  },
		  "color": "#B24DBD",
		  "shape": "circle",
		  "size": {
			"min": 6,
			"max": 13,
			"growthPerDay": 1
		  },
		  "name": "spirula-2412*2",
		  "innerRotation": 0.12132429196995495,
		  "model": "Spirula-10",
		  "stage": 0
		},
		{
		  "birth": 2412,
		  "distance": 368,
		  "angleToOrigine": 0.199908117376725,
		  "position": {
			"x": 360,
			"y": -74
		  },
		  "color": "#B24DBD",
		  "shape": "circle",
		  "size": {
			"min": 6,
			"max": 13,
			"growthPerDay": 1
		  },
		  "name": "spirula-2412*3",
		  "innerRotation": 5.028992424883643,
		  "model": "Spirula-10",
		  "stage": 0
		},
		{
		  "birth": 2412,
		  "distance": 849,
		  "angleToOrigine": 0.632306317994162,
		  "position": {
			"x": 684,
			"y": -502
		  },
		  "color": "#B24DBD",
		  "shape": "circle",
		  "size": {
			"min": 6,
			"max": 13,
			"growthPerDay": 1
		  },
		  "name": "spirula-2412*4",
		  "innerRotation": 3.965611202032998,
		  "model": "Spirula-10",
		  "stage": 0
		},
		{
		  "birth": 2412,
		  "distance": 415,
		  "angleToOrigine": 2.032998850096412,
		  "position": {
			"x": -186,
			"y": -372
		  },
		  "color": "#B24DBD",
		  "shape": "circle",
		  "size": {
			"min": 6,
			"max": 13,
			"growthPerDay": 1
		  },
		  "name": "spirula-2412*5",
		  "innerRotation": 5.711390290637748,
		  "model": "Spirula-10",
		  "stage": 0
		},
		{
		  "birth": 2412,
		  "distance": 796,
		  "angleToOrigine": 0.9982067608042248,
		  "position": {
			"x": 431,
			"y": -670
		  },
		  "color": "#B24DBD",
		  "shape": "circle",
		  "size": {
			"min": 6,
			"max": 13,
			"growthPerDay": 1
		  },
		  "name": "spirula-2412*6",
		  "innerRotation": 5.866540683502832,
		  "model": "Spirula-10",
		  "stage": 0
		},
		{
		  "birth": 2412,
		  "distance": 377,
		  "angleToOrigine": 2.069855857213537,
		  "position": {
			"x": -181,
			"y": -332
		  },
		  "color": "#B24DBD",
		  "shape": "circle",
		  "size": {
			"min": 6,
			"max": 13,
			"growthPerDay": 1
		  },
		  "name": "spirula-2412*7",
		  "innerRotation": 4.219414805703987,
		  "model": "Spirula-10",
		  "stage": 0
		},
		{
		  "birth": 2412,
		  "distance": 496,
		  "angleToOrigine": -1.2062383315543677,
		  "position": {
			"x": 176,
			"y": 463
		  },
		  "color": "#B24DBD",
		  "shape": "circle",
		  "size": {
			"min": 6,
			"max": 13,
			"growthPerDay": 1
		  },
		  "name": "spirula-2412*9",
		  "innerRotation": 5.808148168292571,
		  "model": "Spirula-10",
		  "stage": 0
		},
		{
		  "birth": 2412,
		  "distance": 218,
		  "angleToOrigine": 0.11740627505496064,
		  "position": {
			"x": 216,
			"y": -26
		  },
		  "color": "#B24DBD",
		  "shape": "circle",
		  "size": {
			"min": 6,
			"max": 13,
			"growthPerDay": 1
		  },
		  "name": "spirula-2412*10",
		  "innerRotation": 1.2574801564696172,
		  "model": "Spirula-10",
		  "stage": 0
		},
		{
		  "birth": 2413,
		  "distance": 1476,
		  "angleToOrigine": 0.39002989870597776,
		  "position": {
			"x": 1365,
			"y": -562
		  },
		  "color": "#B24DBD",
		  "shape": "circle",
		  "size": {
			"min": 6,
			"max": 13,
			"growthPerDay": 1
		  },
		  "name": "spirula-2413*5",
		  "innerRotation": 3.7869478150923954,
		  "model": "Spirula-10",
		  "stage": 0
		},
		{
		  "birth": 2413,
		  "distance": 1607,
		  "angleToOrigine": 0.3898561272789092,
		  "position": {
			"x": 1486,
			"y": -611
		  },
		  "color": "#B24DBD",
		  "shape": "circle",
		  "size": {
			"min": 6,
			"max": 13,
			"growthPerDay": 1
		  },
		  "name": "spirula-2413*9",
		  "innerRotation": 2.8066905651548866,
		  "model": "Spirula-10",
		  "stage": 0
		},
		{
		  "birth": 2413,
		  "distance": 1633,
		  "angleToOrigine": 0.37064505415600635,
		  "position": {
			"x": 1522,
			"y": -592
		  },
		  "color": "#B24DBD",
		  "shape": "circle",
		  "size": {
			"min": 6,
			"max": 13,
			"growthPerDay": 1
		  },
		  "name": "spirula-2413*12",
		  "innerRotation": 3.243981294291266,
		  "model": "Spirula-10",
		  "stage": 0
		},
		{
		  "birth": 2413,
		  "distance": 1333,
		  "angleToOrigine": -0.16770803482940297,
		  "position": {
			"x": 1314,
			"y": 222
		  },
		  "color": "#B24DBD",
		  "shape": "circle",
		  "size": {
			"min": 6,
			"max": 13,
			"growthPerDay": 1
		  },
		  "name": "spirula-2413*4",
		  "innerRotation": 4.338916860135145,
		  "model": "Spirula-10",
		  "stage": 0
		},
		{
		  "birth": 2413,
		  "distance": 1583,
		  "angleToOrigine": -0.22696921547798576,
		  "position": {
			"x": 1542,
			"y": 356
		  },
		  "color": "#B24DBD",
		  "shape": "circle",
		  "size": {
			"min": 6,
			"max": 13,
			"growthPerDay": 1
		  },
		  "name": "spirula-2413*5",
		  "innerRotation": 3.11406301903869,
		  "model": "Spirula-10",
		  "stage": 0
		},
		{
		  "birth": 2413,
		  "distance": 1520,
		  "angleToOrigine": -0.194365266095018,
		  "position": {
			"x": 1491,
			"y": 293
		  },
		  "color": "#B24DBD",
		  "shape": "circle",
		  "size": {
			"min": 6,
			"max": 13,
			"growthPerDay": 1
		  },
		  "name": "spirula-2413*6",
		  "innerRotation": 3.796489861318372,
		  "model": "Spirula-10",
		  "stage": 0
		},
		{
		  "birth": 2413,
		  "distance": 1421,
		  "angleToOrigine": -0.21830474667307287,
		  "position": {
			"x": 1387,
			"y": 307
		  },
		  "color": "#B24DBD",
		  "shape": "circle",
		  "size": {
			"min": 6,
			"max": 13,
			"growthPerDay": 1
		  },
		  "name": "spirula-2413*7",
		  "innerRotation": 2.133661636376493,
		  "model": "Spirula-10",
		  "stage": 0
		},
		{
		  "birth": 2413,
		  "distance": 1223,
		  "angleToOrigine": 1.5192513114780768,
		  "position": {
			"x": 63,
			"y": -1222
		  },
		  "color": "#B24DBD",
		  "shape": "circle",
		  "size": {
			"min": 6,
			"max": 13,
			"growthPerDay": 1
		  },
		  "name": "spirula-2413*3",
		  "innerRotation": 3.7584657602522538,
		  "model": "Spirula-10",
		  "stage": 0
		},
		{
		  "birth": 2413,
		  "distance": 1172,
		  "angleToOrigine": -1.5427335203617174,
		  "position": {
			"x": 32,
			"y": 1171
		  },
		  "color": "#B24DBD",
		  "shape": "circle",
		  "size": {
			"min": 6,
			"max": 13,
			"growthPerDay": 1
		  },
		  "name": "spirula-2413*4",
		  "innerRotation": 4.174849568599261,
		  "model": "Spirula-10",
		  "stage": 0
		},
		{
		  "birth": 2413,
		  "distance": 1718,
		  "angleToOrigine": -1.456437000933801,
		  "position": {
			"x": 196,
			"y": 1706
		  },
		  "color": "#B24DBD",
		  "shape": "circle",
		  "size": {
			"min": 6,
			"max": 13,
			"growthPerDay": 1
		  },
		  "name": "spirula-2413*7",
		  "innerRotation": 2.3752312005335265,
		  "model": "Spirula-10",
		  "stage": 0
		},
		{
		  "birth": 2413,
		  "distance": 1360,
		  "angleToOrigine": -1.136410786634008,
		  "position": {
			"x": 572,
			"y": 1233
		  },
		  "color": "#B24DBD",
		  "shape": "circle",
		  "size": {
			"min": 6,
			"max": 13,
			"growthPerDay": 1
		  },
		  "name": "spirula-2413*8",
		  "innerRotation": 3.195024169793,
		  "model": "Spirula-10",
		  "stage": 0
		},
		{
		  "birth": 2413,
		  "distance": 1492,
		  "angleToOrigine": 1.550976639412479,
		  "position": {
			"x": 29,
			"y": -1492
		  },
		  "color": "#B24DBD",
		  "shape": "circle",
		  "size": {
			"min": 6,
			"max": 13,
			"growthPerDay": 1
		  },
		  "name": "spirula-2413*9",
		  "innerRotation": 4.098741100891149,
		  "model": "Spirula-10",
		  "stage": 0
		},
		{
		  "birth": 2413,
		  "distance": 1157,
		  "angleToOrigine": -1.2368724607094836,
		  "position": {
			"x": 379,
			"y": 1093
		  },
		  "color": "#B24DBD",
		  "shape": "circle",
		  "size": {
			"min": 6,
			"max": 13,
			"growthPerDay": 1
		  },
		  "name": "spirula-2413*10",
		  "innerRotation": 4.09468954955897,
		  "model": "Spirula-10",
		  "stage": 0
		},
		{
		  "birth": 2413,
		  "distance": 1527,
		  "angleToOrigine": 1.2958266588111544,
		  "position": {
			"x": 414,
			"y": -1470
		  },
		  "color": "#B24DBD",
		  "shape": "circle",
		  "size": {
			"min": 6,
			"max": 13,
			"growthPerDay": 1
		  },
		  "name": "spirula-2413*3",
		  "innerRotation": 1.4105155262944513,
		  "model": "Spirula-10",
		  "stage": 0
		},
		{
		  "birth": 2413,
		  "distance": 1752,
		  "angleToOrigine": 1.2499585973386926,
		  "position": {
			"x": 552,
			"y": -1663
		  },
		  "color": "#B24DBD",
		  "shape": "circle",
		  "size": {
			"min": 6,
			"max": 13,
			"growthPerDay": 1
		  },
		  "name": "spirula-2413*5",
		  "innerRotation": 4.403751817582386,
		  "model": "Spirula-10",
		  "stage": 0
		},
		{
		  "birth": 2413,
		  "distance": 1712,
		  "angleToOrigine": 1.595940726947514,
		  "position": {
			"x": -44,
			"y": -1712
		  },
		  "color": "#B24DBD",
		  "shape": "circle",
		  "size": {
			"min": 6,
			"max": 13,
			"growthPerDay": 1
		  },
		  "name": "spirula-2413*10",
		  "innerRotation": 1.972283190310642,
		  "model": "Spirula-10",
		  "stage": 0
		},
		{
		  "birth": 2414,
		  "distance": 1281,
		  "angleToOrigine": -0.9638086627484886,
		  "position": {
			"x": 730,
			"y": 1052
		  },
		  "color": "#B24DBD",
		  "shape": "circle",
		  "size": {
			"min": 6,
			"max": 13,
			"growthPerDay": 1
		  },
		  "name": "spirula-2414*6",
		  "innerRotation": 4.312750840435165,
		  "model": "Spirula-10",
		  "stage": 0
		},
		{
		  "birth": 2414,
		  "distance": 1138,
		  "angleToOrigine": 1.4912680229499684,
		  "position": {
			"x": 90,
			"y": -1135
		  },
		  "color": "#B24DBD",
		  "shape": "circle",
		  "size": {
			"min": 6,
			"max": 13,
			"growthPerDay": 1
		  },
		  "name": "spirula-2414*7",
		  "innerRotation": 2.344273822848655,
		  "model": "Spirula-10",
		  "stage": 0
		},
		{
		  "birth": 2414,
		  "distance": 952,
		  "angleToOrigine": -1.4098085130240892,
		  "position": {
			"x": 152,
			"y": 939
		  },
		  "color": "#B24DBD",
		  "shape": "circle",
		  "size": {
			"min": 6,
			"max": 13,
			"growthPerDay": 1
		  },
		  "name": "spirula-2414*2",
		  "innerRotation": 4.1142988023242415,
		  "model": "Spirula-10",
		  "stage": 0
		},
		{
		  "birth": 2414,
		  "distance": 1041,
		  "angleToOrigine": 1.0774717522283261,
		  "position": {
			"x": 492,
			"y": -917
		  },
		  "color": "#B24DBD",
		  "shape": "circle",
		  "size": {
			"min": 6,
			"max": 13,
			"growthPerDay": 1
		  },
		  "name": "spirula-2414*3",
		  "innerRotation": 3.1413115000983516,
		  "model": "Spirula-10",
		  "stage": 0
		},
		{
		  "birth": 2414,
		  "distance": 698,
		  "angleToOrigine": -0.9998156924320277,
		  "position": {
			"x": 377,
			"y": 587
		  },
		  "color": "#B24DBD",
		  "shape": "circle",
		  "size": {
			"min": 6,
			"max": 13,
			"growthPerDay": 1
		  },
		  "name": "spirula-2414*4",
		  "innerRotation": 3.874706131044542,
		  "model": "Spirula-10",
		  "stage": 0
		},
		{
		  "birth": 2414,
		  "distance": 897,
		  "angleToOrigine": 1.4361725162974726,
		  "position": {
			"x": 120,
			"y": -889
		  },
		  "color": "#B24DBD",
		  "shape": "circle",
		  "size": {
			"min": 6,
			"max": 13,
			"growthPerDay": 1
		  },
		  "name": "spirula-2414*5",
		  "innerRotation": 3.888668630562713,
		  "model": "Spirula-10",
		  "stage": 0
		},
		{
		  "birth": 2414,
		  "distance": 1305,
		  "angleToOrigine": 1.2370204501432447,
		  "position": {
			"x": 427,
			"y": -1233
		  },
		  "color": "#B24DBD",
		  "shape": "circle",
		  "size": {
			"min": 6,
			"max": 13,
			"growthPerDay": 1
		  },
		  "name": "spirula-2414*6",
		  "innerRotation": 3.0309545639988382,
		  "model": "Spirula-10",
		  "stage": 0
		},
		{
		  "birth": 2414,
		  "distance": 1052,
		  "angleToOrigine": 0.8196053471687916,
		  "position": {
			"x": 718,
			"y": -769
		  },
		  "color": "#B24DBD",
		  "shape": "circle",
		  "size": {
			"min": 6,
			"max": 13,
			"growthPerDay": 1
		  },
		  "name": "spirula-2414*7",
		  "innerRotation": 0.7655804254628931,
		  "model": "Spirula-10",
		  "stage": 0
		},
		{
		  "birth": 2413,
		  "distance": 997,
		  "angleToOrigine": -0.4921939228917384,
		  "position": {
			"x": 878,
			"y": 471
		  },
		  "color": "#B24DBD",
		  "shape": "circle",
		  "size": {
			"min": 6,
			"max": 13,
			"growthPerDay": 1
		  },
		  "name": "spirula-2410*4",
		  "innerRotation": 2.8980957765753033,
		  "model": "Spirula-10",
		  "stage": 1
		},
		{
		  "birth": 2413,
		  "distance": 1366,
		  "angleToOrigine": -0.11820153645380832,
		  "position": {
			"x": 1356,
			"y": 161
		  },
		  "color": "#B24DBD",
		  "shape": "circle",
		  "size": {
			"min": 6,
			"max": 13,
			"growthPerDay": 1
		  },
		  "name": "spirula-2410*5",
		  "innerRotation": 4.286980871218764,
		  "model": "Spirula-10",
		  "stage": 1
		},
		{
		  "birth": 2413,
		  "distance": 1392,
		  "angleToOrigine": -0.16054291209563207,
		  "position": {
			"x": 1374,
			"y": 222
		  },
		  "color": "#B24DBD",
		  "shape": "circle",
		  "size": {
			"min": 6,
			"max": 13,
			"growthPerDay": 1
		  },
		  "name": "spirula-2410*6",
		  "innerRotation": 2.946769966925917,
		  "model": "Spirula-10",
		  "stage": 1
		},
		{
		  "birth": 2413,
		  "distance": 1127,
		  "angleToOrigine": 0.10131370616494323,
		  "position": {
			"x": 1121,
			"y": -114
		  },
		  "color": "#B24DBD",
		  "shape": "circle",
		  "size": {
			"min": 6,
			"max": 13,
			"growthPerDay": 1
		  },
		  "name": "spirula-2410*8",
		  "innerRotation": 2.7600842801752954,
		  "model": "Spirula-10",
		  "stage": 1
		},
		{
		  "birth": 2413,
		  "distance": 1367,
		  "angleToOrigine": -0.26743454761434565,
		  "position": {
			"x": 1318,
			"y": 361
		  },
		  "color": "#B24DBD",
		  "shape": "circle",
		  "size": {
			"min": 6,
			"max": 13,
			"growthPerDay": 1
		  },
		  "name": "spirula-2410*10",
		  "innerRotation": 3.2818188858112656,
		  "model": "Spirula-10",
		  "stage": 1
		},
		{
		  "birth": 2413,
		  "distance": 1463,
		  "angleToOrigine": 1.21315804228696,
		  "position": {
			"x": 512,
			"y": -1371
		  },
		  "color": "#B24DBD",
		  "shape": "circle",
		  "size": {
			"min": 6,
			"max": 13,
			"growthPerDay": 1
		  },
		  "name": "spirula-2410*2",
		  "innerRotation": 3.8158406569493817,
		  "model": "Spirula-10",
		  "stage": 1
		},
		{
		  "birth": 2413,
		  "distance": 1605,
		  "angleToOrigine": 0.9887773761031872,
		  "position": {
			"x": 882,
			"y": -1341
		  },
		  "color": "#B24DBD",
		  "shape": "circle",
		  "size": {
			"min": 6,
			"max": 13,
			"growthPerDay": 1
		  },
		  "name": "spirula-2410*5",
		  "innerRotation": 3.302169717055135,
		  "model": "Spirula-10",
		  "stage": 1
		},
		{
		  "birth": 2412,
		  "distance": 282,
		  "angleToOrigine": 1.32268287769822,
		  "position": {
			"x": 69,
			"y": -274
		  },
		  "color": "#B24DBD",
		  "shape": "circle",
		  "size": {
			"min": 6,
			"max": 13,
			"growthPerDay": 1
		  },
		  "name": "spirula-2409*3",
		  "innerRotation": 2.0017661764337995,
		  "model": "Spirula-10",
		  "stage": 1
		},
		{
		  "birth": 2412,
		  "distance": 1181,
		  "angleToOrigine": 0.3699269142534443,
		  "position": {
			"x": 1101,
			"y": -427
		  },
		  "color": "#B24DBD",
		  "shape": "circle",
		  "size": {
			"min": 6,
			"max": 13,
			"growthPerDay": 1
		  },
		  "name": "spirula-2409*4",
		  "innerRotation": 2.4061041275084065,
		  "model": "Spirula-10",
		  "stage": 1
		},
		{
		  "birth": 2412,
		  "distance": 762,
		  "angleToOrigine": 1.0688898837429033,
		  "position": {
			"x": 366,
			"y": -669
		  },
		  "color": "#B24DBD",
		  "shape": "circle",
		  "size": {
			"min": 6,
			"max": 13,
			"growthPerDay": 1
		  },
		  "name": "spirula-2409*5",
		  "innerRotation": 0.25585829055949927,
		  "model": "Spirula-10",
		  "stage": 1
		},
		{
		  "birth": 2412,
		  "distance": 1780,
		  "angleToOrigine": 0.13510052180347318,
		  "position": {
			"x": 1763,
			"y": -240
		  },
		  "color": "#B24DBD",
		  "shape": "circle",
		  "size": {
			"min": 6,
			"max": 13,
			"growthPerDay": 1
		  },
		  "name": "spirula-2409*9",
		  "innerRotation": 3.3962912690366704,
		  "model": "Spirula-10",
		  "stage": 1
		},
		{
		  "birth": 2412,
		  "distance": 388,
		  "angleToOrigine": -0.6420581083518465,
		  "position": {
			"x": 310,
			"y": 232
		  },
		  "color": "#B24DBD",
		  "shape": "circle",
		  "size": {
			"min": 6,
			"max": 13,
			"growthPerDay": 1
		  },
		  "name": "spirula-2409*3",
		  "innerRotation": 3.4466417727088716,
		  "model": "Spirula-10",
		  "stage": 1
		},
		{
		  "birth": 2412,
		  "distance": 599,
		  "angleToOrigine": 1.1850395940500202,
		  "position": {
			"x": 225,
			"y": -555
		  },
		  "color": "#B24DBD",
		  "shape": "circle",
		  "size": {
			"min": 6,
			"max": 13,
			"growthPerDay": 1
		  },
		  "name": "spirula-2409*4",
		  "innerRotation": 4.648079127001598,
		  "model": "Spirula-10",
		  "stage": 1
		},
		{
		  "birth": 2412,
		  "distance": 352,
		  "angleToOrigine": 1.4573613349876804,
		  "position": {
			"x": 39,
			"y": -350
		  },
		  "color": "#B24DBD",
		  "shape": "circle",
		  "size": {
			"min": 6,
			"max": 13,
			"growthPerDay": 1
		  },
		  "name": "spirula-2409*7",
		  "innerRotation": 5.773955598330423,
		  "model": "Spirula-10",
		  "stage": 1
		},
		{
		  "birth": 2412,
		  "distance": 139,
		  "angleToOrigine": 1.5561988235838364,
		  "position": {
			"x": 2,
			"y": -139
		  },
		  "color": "#B24DBD",
		  "shape": "circle",
		  "size": {
			"min": 6,
			"max": 13,
			"growthPerDay": 1
		  },
		  "name": "spirula-2409*9",
		  "innerRotation": 0.5568296917817088,
		  "model": "Spirula-10",
		  "stage": 1
		},
		{
		  "birth": 2412,
		  "distance": 167,
		  "angleToOrigine": 0.5221887012066232,
		  "position": {
			"x": 144,
			"y": -84
		  },
		  "color": "#B24DBD",
		  "shape": "circle",
		  "size": {
			"min": 6,
			"max": 13,
			"growthPerDay": 1
		  },
		  "name": "spirula-2409*12",
		  "innerRotation": 3.921107353550011,
		  "model": "Spirula-10",
		  "stage": 1
		}
	  ],
	  "rocks": [
		{
		  "size": 400,
		  "distance": 500,
		  "angleToOrigine": -0.3,
		  "name": "bigOne",
		  "innerRotation": 0,
		  "colors": "#998877",
		  "repeat": 4,
		  "matrix": [
			{
			  "x": -0.815,
			  "y": -0.605
			},
			{
			  "x": -0.85,
			  "y": -0.495
			},
			{
			  "x": -0.815,
			  "y": -0.395
			},
			{
			  "x": -0.76,
			  "y": -0.315
			},
			{
			  "x": -0.765,
			  "y": -0.23
			},
			{
			  "x": -0.845,
			  "y": -0.06
			},
			{
			  "x": -0.835,
			  "y": -0.01
			},
			{
			  "x": -0.8,
			  "y": 0.065
			},
			{
			  "x": -0.74,
			  "y": 0.145
			},
			{
			  "x": -0.72,
			  "y": 0.225
			},
			{
			  "x": -0.695,
			  "y": 0.53
			},
			{
			  "x": -0.63,
			  "y": 0.685
			},
			{
			  "x": -0.48,
			  "y": 0.805
			},
			{
			  "x": -0.235,
			  "y": 0.8
			},
			{
			  "x": -0.02,
			  "y": 0.72
			},
			{
			  "x": 0.23,
			  "y": 0.65
			},
			{
			  "x": 0.405,
			  "y": 0.63
			},
			{
			  "x": 0.54,
			  "y": 0.69
			},
			{
			  "x": 0.63,
			  "y": 0.66
			},
			{
			  "x": 0.625,
			  "y": 0.585
			},
			{
			  "x": 0.585,
			  "y": 0.535
			},
			{
			  "x": 0.565,
			  "y": 0.47
			},
			{
			  "x": 0.655,
			  "y": 0.485
			},
			{
			  "x": 0.725,
			  "y": 0.495
			},
			{
			  "x": 0.805,
			  "y": 0.53
			},
			{
			  "x": 0.855,
			  "y": 0.475
			},
			{
			  "x": 0.845,
			  "y": 0.385
			},
			{
			  "x": 0.755,
			  "y": 0.305
			},
			{
			  "x": 0.705,
			  "y": 0.19
			},
			{
			  "x": 0.705,
			  "y": 0.02
			},
			{
			  "x": 0.645,
			  "y": -0.05
			},
			{
			  "x": 0.575,
			  "y": -0.19
			},
			{
			  "x": 0.62,
			  "y": -0.295
			},
			{
			  "x": 0.625,
			  "y": -0.405
			},
			{
			  "x": 0.52,
			  "y": -0.41
			},
			{
			  "x": 0.455,
			  "y": -0.34
			},
			{
			  "x": 0.34,
			  "y": -0.375
			},
			{
			  "x": 0.33,
			  "y": -0.46
			},
			{
			  "x": 0.32,
			  "y": -0.56
			},
			{
			  "x": 0.17,
			  "y": -0.61
			},
			{
			  "x": 0,
			  "y": -0.56
			},
			{
			  "x": -0.195,
			  "y": -0.635
			},
			{
			  "x": -0.285,
			  "y": -0.745
			},
			{
			  "x": -0.4,
			  "y": -0.8
			},
			{
			  "x": -0.54,
			  "y": -0.745
			},
			{
			  "x": -0.675,
			  "y": -0.55
			},
			{
			  "x": -0.815,
			  "y": -0.605
			}
		  ],
		  "position": {
			"x": 477,
			"y": 147
		  }
		},
		{
		  "size": 350,
		  "distance": 230,
		  "angleToOrigine": 5.2,
		  "name": "Everest",
		  "innerRotation": 2.8,
		  "colors": "#998877",
		  "repeat": 4,
		  "matrix": [
			{
			  "x": -0.205,
			  "y": -0.775
			},
			{
			  "x": -0.06,
			  "y": -0.78
			},
			{
			  "x": 0.12,
			  "y": -0.785
			},
			{
			  "x": 0.16,
			  "y": -0.72
			},
			{
			  "x": 0.17,
			  "y": -0.63
			},
			{
			  "x": 0.19,
			  "y": -0.525
			},
			{
			  "x": 0.28,
			  "y": -0.425
			},
			{
			  "x": 0.3,
			  "y": -0.32
			},
			{
			  "x": 0.425,
			  "y": -0.245
			},
			{
			  "x": 0.46,
			  "y": -0.145
			},
			{
			  "x": 0.45,
			  "y": -0.055
			},
			{
			  "x": 0.405,
			  "y": 0.06
			},
			{
			  "x": 0.42,
			  "y": 0.135
			},
			{
			  "x": 0.45,
			  "y": 0.22
			},
			{
			  "x": 0.535,
			  "y": 0.265
			},
			{
			  "x": 0.6,
			  "y": 0.355
			},
			{
			  "x": 0.625,
			  "y": 0.485
			},
			{
			  "x": 0.595,
			  "y": 0.57
			},
			{
			  "x": 0.52,
			  "y": 0.6
			},
			{
			  "x": 0.42,
			  "y": 0.55
			},
			{
			  "x": 0.375,
			  "y": 0.57
			},
			{
			  "x": 0.325,
			  "y": 0.6
			},
			{
			  "x": 0.295,
			  "y": 0.69
			},
			{
			  "x": 0.235,
			  "y": 0.745
			},
			{
			  "x": 0.045,
			  "y": 0.79
			},
			{
			  "x": -0.215,
			  "y": 0.75
			},
			{
			  "x": -0.38,
			  "y": 0.665
			},
			{
			  "x": -0.48,
			  "y": 0.585
			},
			{
			  "x": -0.595,
			  "y": 0.5
			},
			{
			  "x": -0.62,
			  "y": 0.39
			},
			{
			  "x": -0.575,
			  "y": 0.25
			},
			{
			  "x": -0.53,
			  "y": 0.125
			},
			{
			  "x": -0.35,
			  "y": 0.005
			},
			{
			  "x": -0.24,
			  "y": -0.135
			},
			{
			  "x": -0.215,
			  "y": -0.315
			},
			{
			  "x": -0.18,
			  "y": -0.55
			},
			{
			  "x": -0.23,
			  "y": -0.635
			},
			{
			  "x": -0.275,
			  "y": -0.73
			},
			{
			  "x": -0.205,
			  "y": -0.775
			}
		  ],
		  "position": {
			"x": 107,
			"y": 203
		  }
		},
		{
		  "size": 320,
		  "distance": 620,
		  "angleToOrigine": 2.5,
		  "name": "kilimandjaro",
		  "innerRotation": 1,
		  "colors": "#c88884",
		  "repeat": 4,
		  "matrix": [
			{
			  "x": -0.45,
			  "y": -0.615
			},
			{
			  "x": -0.475,
			  "y": -0.515
			},
			{
			  "x": -0.485,
			  "y": -0.405
			},
			{
			  "x": -0.46,
			  "y": -0.32
			},
			{
			  "x": -0.445,
			  "y": -0.24
			},
			{
			  "x": -0.495,
			  "y": -0.15
			},
			{
			  "x": -0.555,
			  "y": -0.085
			},
			{
			  "x": -0.625,
			  "y": -0.01
			},
			{
			  "x": -0.705,
			  "y": 0.085
			},
			{
			  "x": -0.695,
			  "y": 0.185
			},
			{
			  "x": -0.65,
			  "y": 0.25
			},
			{
			  "x": -0.585,
			  "y": 0.305
			},
			{
			  "x": -0.54,
			  "y": 0.355
			},
			{
			  "x": -0.41,
			  "y": 0.39
			},
			{
			  "x": -0.475,
			  "y": 0.6
			},
			{
			  "x": -0.52,
			  "y": 0.695
			},
			{
			  "x": -0.47,
			  "y": 0.795
			},
			{
			  "x": -0.35,
			  "y": 0.845
			},
			{
			  "x": -0.06,
			  "y": 0.87
			},
			{
			  "x": 0.135,
			  "y": 0.795
			},
			{
			  "x": 0.31,
			  "y": 0.69
			},
			{
			  "x": 0.55,
			  "y": 0.505
			},
			{
			  "x": 0.685,
			  "y": 0.265
			},
			{
			  "x": 0.705,
			  "y": 0.15
			},
			{
			  "x": 0.51,
			  "y": 0.04
			},
			{
			  "x": 0.385,
			  "y": -0.02
			},
			{
			  "x": 0.2,
			  "y": -0.085
			},
			{
			  "x": 0.15,
			  "y": -0.21
			},
			{
			  "x": 0.235,
			  "y": -0.355
			},
			{
			  "x": 0.32,
			  "y": -0.425
			},
			{
			  "x": 0.4,
			  "y": -0.585
			},
			{
			  "x": 0.35,
			  "y": -0.705
			},
			{
			  "x": 0.25,
			  "y": -0.83
			},
			{
			  "x": -0.125,
			  "y": -0.87
			},
			{
			  "x": -0.2,
			  "y": -0.785
			},
			{
			  "x": -0.29,
			  "y": -0.705
			},
			{
			  "x": -0.31,
			  "y": -0.64
			},
			{
			  "x": -0.365,
			  "y": -0.605
			},
			{
			  "x": -0.45,
			  "y": -0.615
			}
		  ],
		  "position": {
			"x": -497,
			"y": -372
		  }
		},
		{
		  "size": 315,
		  "distance": 600,
		  "angleToOrigine": 3.4,
		  "name": "Monumental",
		  "innerRotation": 0.75,
		  "colors": "#c77774",
		  "repeat": 4,
		  "matrix": [
			{
			  "x": -0.36,
			  "y": -0.725
			},
			{
			  "x": -0.18,
			  "y": -0.79
			},
			{
			  "x": -0.045,
			  "y": -0.785
			},
			{
			  "x": 0.215,
			  "y": -0.745
			},
			{
			  "x": 0.35,
			  "y": -0.68
			},
			{
			  "x": 0.385,
			  "y": -0.585
			},
			{
			  "x": 0.535,
			  "y": -0.465
			},
			{
			  "x": 0.625,
			  "y": -0.33
			},
			{
			  "x": 0.625,
			  "y": -0.21
			},
			{
			  "x": 0.63,
			  "y": -0.02
			},
			{
			  "x": 0.575,
			  "y": 0.11
			},
			{
			  "x": 0.5,
			  "y": 0.15
			},
			{
			  "x": 0.385,
			  "y": 0.13
			},
			{
			  "x": 0.335,
			  "y": 0.185
			},
			{
			  "x": 0.35,
			  "y": 0.22
			},
			{
			  "x": 0.385,
			  "y": 0.255
			},
			{
			  "x": 0.41,
			  "y": 0.31
			},
			{
			  "x": 0.395,
			  "y": 0.345
			},
			{
			  "x": 0.325,
			  "y": 0.345
			},
			{
			  "x": 0.255,
			  "y": 0.31
			},
			{
			  "x": 0.235,
			  "y": 0.35
			},
			{
			  "x": 0.26,
			  "y": 0.39
			},
			{
			  "x": 0.325,
			  "y": 0.43
			},
			{
			  "x": 0.39,
			  "y": 0.44
			},
			{
			  "x": 0.455,
			  "y": 0.43
			},
			{
			  "x": 0.465,
			  "y": 0.45
			},
			{
			  "x": 0.46,
			  "y": 0.53
			},
			{
			  "x": 0.425,
			  "y": 0.575
			},
			{
			  "x": 0.405,
			  "y": 0.605
			},
			{
			  "x": 0.415,
			  "y": 0.66
			},
			{
			  "x": 0.405,
			  "y": 0.73
			},
			{
			  "x": 0.32,
			  "y": 0.765
			},
			{
			  "x": 0.175,
			  "y": 0.795
			},
			{
			  "x": 0.04,
			  "y": 0.765
			},
			{
			  "x": -0.09,
			  "y": 0.695
			},
			{
			  "x": -0.27,
			  "y": 0.615
			},
			{
			  "x": -0.405,
			  "y": 0.585
			},
			{
			  "x": -0.515,
			  "y": 0.415
			},
			{
			  "x": -0.54,
			  "y": 0.235
			},
			{
			  "x": -0.51,
			  "y": 0.03
			},
			{
			  "x": -0.6,
			  "y": 0.005
			},
			{
			  "x": -0.625,
			  "y": -0.085
			},
			{
			  "x": -0.615,
			  "y": -0.22
			},
			{
			  "x": -0.57,
			  "y": -0.305
			},
			{
			  "x": -0.48,
			  "y": -0.29
			},
			{
			  "x": -0.415,
			  "y": -0.41
			},
			{
			  "x": -0.39,
			  "y": -0.54
			},
			{
			  "x": -0.4,
			  "y": -0.645
			},
			{
			  "x": -0.36,
			  "y": -0.725
			}
		  ],
		  "position": {
			"x": -581,
			"y": 153
		  }
		},
		{
		  "size": 515,
		  "distance": 900,
		  "angleToOrigine": 0.4,
		  "name": "moloch",
		  "innerRotation": 0.75,
		  "colors": "#c76674",
		  "repeat": 3,
		  "matrix": [
			{
			  "x": -0.32,
			  "y": -0.795
			},
			{
			  "x": -0.435,
			  "y": -0.715
			},
			{
			  "x": -0.54,
			  "y": -0.63
			},
			{
			  "x": -0.59,
			  "y": -0.535
			},
			{
			  "x": -0.68,
			  "y": -0.425
			},
			{
			  "x": -0.915,
			  "y": -0.315
			},
			{
			  "x": -0.935,
			  "y": -0.14
			},
			{
			  "x": -0.885,
			  "y": 0.01
			},
			{
			  "x": -0.84,
			  "y": 0.115
			},
			{
			  "x": -0.79,
			  "y": 0.23
			},
			{
			  "x": -0.805,
			  "y": 0.335
			},
			{
			  "x": -0.83,
			  "y": 0.47
			},
			{
			  "x": -0.785,
			  "y": 0.615
			},
			{
			  "x": -0.68,
			  "y": 0.765
			},
			{
			  "x": -0.54,
			  "y": 0.83
			},
			{
			  "x": -0.345,
			  "y": 0.885
			},
			{
			  "x": -0.02,
			  "y": 0.905
			},
			{
			  "x": 0.3,
			  "y": 0.905
			},
			{
			  "x": 0.59,
			  "y": 0.845
			},
			{
			  "x": 0.71,
			  "y": 0.695
			},
			{
			  "x": 0.8,
			  "y": 0.525
			},
			{
			  "x": 0.865,
			  "y": 0.4
			},
			{
			  "x": 0.895,
			  "y": 0.185
			},
			{
			  "x": 0.815,
			  "y": 0.09
			},
			{
			  "x": 0.655,
			  "y": 0
			},
			{
			  "x": 0.55,
			  "y": -0.055
			},
			{
			  "x": 0.56,
			  "y": -0.175
			},
			{
			  "x": 0.67,
			  "y": -0.255
			},
			{
			  "x": 0.78,
			  "y": -0.26
			},
			{
			  "x": 0.89,
			  "y": -0.28
			},
			{
			  "x": 0.94,
			  "y": -0.405
			},
			{
			  "x": 0.925,
			  "y": -0.54
			},
			{
			  "x": 0.845,
			  "y": -0.715
			},
			{
			  "x": 0.685,
			  "y": -0.83
			},
			{
			  "x": 0.465,
			  "y": -0.895
			},
			{
			  "x": 0.315,
			  "y": -0.84
			},
			{
			  "x": 0.265,
			  "y": -0.73
			},
			{
			  "x": 0.155,
			  "y": -0.67
			},
			{
			  "x": 0.025,
			  "y": -0.635
			},
			{
			  "x": -0.045,
			  "y": -0.73
			},
			{
			  "x": -0.055,
			  "y": -0.855
			},
			{
			  "x": -0.115,
			  "y": -0.9
			},
			{
			  "x": -0.21,
			  "y": -0.875
			},
			{
			  "x": -0.32,
			  "y": -0.795
			}
		  ],
		  "position": {
			"x": 828,
			"y": -351
		  }
		},
		{
		  "size": 420,
		  "distance": 1000,
		  "angleToOrigine": 4.5,
		  "name": "tortoise",
		  "innerRotation": 1,
		  "colors": "#886655",
		  "repeat": 3,
		  "matrix": [
			{
			  "x": -0.6033333333333334,
			  "y": -0.25
			},
			{
			  "x": -0.5833333333333334,
			  "y": -0.35333333333333333
			},
			{
			  "x": -0.41333333333333333,
			  "y": -0.45
			},
			{
			  "x": -0.26666666666666666,
			  "y": -0.47333333333333333
			},
			{
			  "x": -0.10666666666666667,
			  "y": -0.4633333333333333
			},
			{
			  "x": 0.016666666666666666,
			  "y": -0.5133333333333333
			},
			{
			  "x": 0.16333333333333333,
			  "y": -0.5233333333333333
			},
			{
			  "x": 0.27,
			  "y": -0.45666666666666667
			},
			{
			  "x": 0.38,
			  "y": -0.38666666666666666
			},
			{
			  "x": 0.5166666666666667,
			  "y": -0.31
			},
			{
			  "x": 0.6333333333333333,
			  "y": -0.12
			},
			{
			  "x": 0.64,
			  "y": 0.08333333333333333
			},
			{
			  "x": 0.5033333333333333,
			  "y": 0.27666666666666667
			},
			{
			  "x": 0.31333333333333335,
			  "y": 0.42333333333333334
			},
			{
			  "x": 0.1,
			  "y": 0.5266666666666666
			},
			{
			  "x": -0.12,
			  "y": 0.44666666666666666
			},
			{
			  "x": -0.18333333333333332,
			  "y": 0.2833333333333333
			},
			{
			  "x": -0.20333333333333334,
			  "y": 0.21
			},
			{
			  "x": -0.25666666666666665,
			  "y": 0.18
			},
			{
			  "x": -0.34,
			  "y": 0.16666666666666666
			},
			{
			  "x": -0.3933333333333333,
			  "y": 0.19666666666666666
			},
			{
			  "x": -0.45666666666666667,
			  "y": 0.21
			},
			{
			  "x": -0.5433333333333333,
			  "y": 0.18333333333333332
			},
			{
			  "x": -0.59,
			  "y": 0.12666666666666668
			},
			{
			  "x": -0.62,
			  "y": 0.03333333333333333
			},
			{
			  "x": -0.6366666666666667,
			  "y": -0.056666666666666664
			},
			{
			  "x": -0.6166666666666667,
			  "y": -0.15333333333333332
			},
			{
			  "x": -0.5966666666666667,
			  "y": -0.16333333333333333
			},
			{
			  "x": -0.5266666666666666,
			  "y": -0.17333333333333334
			},
			{
			  "x": -0.47333333333333333,
			  "y": -0.17
			},
			{
			  "x": -0.4266666666666667,
			  "y": -0.17333333333333334
			},
			{
			  "x": -0.39,
			  "y": -0.16
			},
			{
			  "x": -0.42,
			  "y": -0.21
			},
			{
			  "x": -0.4666666666666667,
			  "y": -0.22333333333333333
			},
			{
			  "x": -0.5333333333333333,
			  "y": -0.23333333333333334
			},
			{
			  "x": -0.5666666666666667,
			  "y": -0.24333333333333335
			},
			{
			  "x": -0.6033333333333334,
			  "y": -0.25
			}
		  ],
		  "position": {
			"x": -211,
			"y": 977
		  }
		}
	  ]
	}
  }